Workbook
Name Project_Status: 'Master_Management'!$A$6:$A$12
Name Task_Status: 'Master_Management'!$B$6:$B$12
Name Priority: 'Master_Management'!$C$6:$C$9
Name Health: 'Master_Management'!$D$6:$D$11
Name Issue_Status: 'Master_Management'!$E$6:$E$11
Name Issue_Type: 'Master_Management'!$F$6:$F$11
Name Risk_Status: 'Master_Management'!$G$6:$G$10
Name Billable: 'Master_Management'!$H$6:$H$7
Name Department: 'Master_Management'!$I$6:$I$15
Name Role: 'Master_Management'!$J$6:$J$14
Name Activity_Type: 'Master_Management'!$K$6:$K$12
Name Document_Type: 'Master_Management'!$L$6:$L$13
Name UserIDs: 'Users'!$A$6:$A$300
Name TeamIDs: 'Teams'!$A$6:$A$200
Name ClientIDs: 'Clients'!$A$6:$A$200
Name ProjectIDs: 'Projects'!$A$6:$A$500
Name TaskIDs: 'Tasks'!$A$6:$A$700

Sheet Home
A1: Complete Responsive Project Management Environment
A2: Excel PMO system with desktop, compact, governance and project command views
A3: Home | B3: Exec | C3: Compact | D3: Project | E3: Tasks | F3: Kanban | G3: Gantt | H3: Reports | I3: Master
A5: Start Here
A7: Executive Dashboard | B7: Full desktop PMO dashboard
A8: Compact Dashboard | B8: Smaller-screen quick dashboard
A9: Project Command Center | B9: Single project selector view
A10: Projects | B10: Portfolio master
A11: Tasks | B11: Task tracking
A12: Kanban | B12: Status board
A13: Gantt | B13: Timeline view
A14: Change Requests | B14: Change control
A15: Approvals | B15: Approval tracker
A16: RACI Matrix | B16: Role clarity
A17: Reports | B17: PMO reports

Sheet Portfolio_Dashboard
A1: Portfolio Dashboard
A2: High-standard PMO dashboard for multiple projects
A3: Home | B3: Dashboard | C3: Workspace | D3: Projects | E3: Tasks | F3: Issues | G3: Timesheets | H3: Reports | I3: Master
A5: =COUNTA(tblProjects[Project ID]) | D5: =COUNTIFS(tblProjects[Manual Status],"In Progress") | G5: =COUNTIFS(tblProjects[Auto Health],"At Risk")+COUNTIFS(tblProjects[Auto Health],"Overdue") | J5: =COUNTIFS(tblProjects[Manual Status],"Completed")
A8: Total Projects | D8: Active Projects | G8: At Risk / Overdue | J8: Completed Projects
A10: =COUNTIFS(tblIssues[Status],"<>Closed",tblIssues[Status],"<>Resolved") | D10: =COUNTIFS(tblRisks[Status],"<>Closed") | G10: =SUM(tblTimesheets[Hours]) | J10: =SUM(tblProjects[Actual Cost])-SUM(tblProjects[Budget])
A13: Open Issues | D13: Open Risks | G13: Logged Hours | J13: Budget Variance
A16: Project Health | D16: Task Status | G16: Priority Mix | J16: User Workload
A17: Health | B17: Count | D17: Status | E17: Count | G17: Priority | H17: Count | J17: User | K17: Active Tasks
A18: On Track | B18: =COUNTIF(tblProjects[Auto Health],A18) | D18: On Track | E18: =COUNTIF(tblTasks[Auto Health],D18) | G18: Critical | H18: =COUNTIF(tblTasks[Priority],G18) | J18: =Users!B6 | K18: =Users!I6
A19: At Risk | B19: =COUNTIF(tblProjects[Auto Health],A19) | D19: At Risk | E19: =COUNTIF(tblTasks[Auto Health],D19) | G19: High | H19: =COUNTIF(tblTasks[Priority],G19) | J19: =Users!B7 | K19: =Users!I7
A20: Overdue | B20: =COUNTIF(tblProjects[Auto Health],A20) | D20: Overdue | E20: =COUNTIF(tblTasks[Auto Health],D20) | G20: Medium | H20: =COUNTIF(tblTasks[Priority],G20) | J20: =Users!B8 | K20: =Users!I8
A21: Blocked | B21: =COUNTIF(tblProjects[Auto Health],A21) | D21: Blocked | E21: =COUNTIF(tblTasks[Auto Health],D21) | G21: Low | H21: =COUNTIF(tblTasks[Priority],G21) | J21: =Users!B9 | K21: =Users!I9
A22: Completed | B22: =COUNTIF(tblProjects[Auto Health],A22) | D22: Completed | E22: =COUNTIF(tblTasks[Auto Health],D22) | J22: =Users!B10 | K22: =Users!I10
A23: Not Started | B23: =COUNTIF(tblProjects[Auto Health],A23) | D23: Not Started | E23: =COUNTIF(tblTasks[Auto Health],D23) | J23: =Users!B11 | K23: =Users!I11
A26: Portfolio List
A27: Project ID | B27: Project | C27: Status | D27: Priority | E27: Progress | F27: Health | G27: Open Issues | H27: Open Risks | I27: Hours
A28: =IFERROR(INDEX(tblProjects[Project ID],1),"") | B28: =IFERROR(INDEX(tblProjects[Project Name],1),"") | C28: =IFERROR(INDEX(tblProjects[Manual Status],1),"") | D28: =IFERROR(INDEX(tblProjects[Priority],1),"") | E28: =IFERROR(INDEX(tblProjects[Progress %],1),"") | F28: =IFERROR(INDEX(tblProjects[Auto Health],1),"") | G28: =IFERROR(INDEX(tblProjects[Open Issues],1),"") | H28: =IFERROR(INDEX(tblProjects[Open Risks],1),"") | I28: =IFERROR(INDEX(tblProjects[Logged Hours],1),"")
A29: =IFERROR(INDEX(tblProjects[Project ID],2),"") | B29: =IFERROR(INDEX(tblProjects[Project Name],2),"") | C29: =IFERROR(INDEX(tblProjects[Manual Status],2),"") | D29: =IFERROR(INDEX(tblProjects[Priority],2),"") | E29: =IFERROR(INDEX(tblProjects[Progress %],2),"") | F29: =IFERROR(INDEX(tblProjects[Auto Health],2),"") | G29: =IFERROR(INDEX(tblProjects[Open Issues],2),"") | H29: =IFERROR(INDEX(tblProjects[Open Risks],2),"") | I29: =IFERROR(INDEX(tblProjects[Logged Hours],2),"")
A30: =IFERROR(INDEX(tblProjects[Project ID],3),"") | B30: =IFERROR(INDEX(tblProjects[Project Name],3),"") | C30: =IFERROR(INDEX(tblProjects[Manual Status],3),"") | D30: =IFERROR(INDEX(tblProjects[Priority],3),"") | E30: =IFERROR(INDEX(tblProjects[Progress %],3),"") | F30: =IFERROR(INDEX(tblProjects[Auto Health],3),"") | G30: =IFERROR(INDEX(tblProjects[Open Issues],3),"") | H30: =IFERROR(INDEX(tblProjects[Open Risks],3),"") | I30: =IFERROR(INDEX(tblProjects[Logged Hours],3),"")
A31: =IFERROR(INDEX(tblProjects[Project ID],4),"") | B31: =IFERROR(INDEX(tblProjects[Project Name],4),"") | C31: =IFERROR(INDEX(tblProjects[Manual Status],4),"") | D31: =IFERROR(INDEX(tblProjects[Priority],4),"") | E31: =IFERROR(INDEX(tblProjects[Progress %],4),"") | F31: =IFERROR(INDEX(tblProjects[Auto Health],4),"") | G31: =IFERROR(INDEX(tblProjects[Open Issues],4),"") | H31: =IFERROR(INDEX(tblProjects[Open Risks],4),"") | I31: =IFERROR(INDEX(tblProjects[Logged Hours],4),"")
A32: =IFERROR(INDEX(tblProjects[Project ID],5),"") | B32: =IFERROR(INDEX(tblProjects[Project Name],5),"") | C32: =IFERROR(INDEX(tblProjects[Manual Status],5),"") | D32: =IFERROR(INDEX(tblProjects[Priority],5),"") | E32: =IFERROR(INDEX(tblProjects[Progress %],5),"") | F32: =IFERROR(INDEX(tblProjects[Auto Health],5),"") | G32: =IFERROR(INDEX(tblProjects[Open Issues],5),"") | H32: =IFERROR(INDEX(tblProjects[Open Risks],5),"") | I32: =IFERROR(INDEX(tblProjects[Logged Hours],5),"")
A33: =IFERROR(INDEX(tblProjects[Project ID],6),"") | B33: =IFERROR(INDEX(tblProjects[Project Name],6),"") | C33: =IFERROR(INDEX(tblProjects[Manual Status],6),"") | D33: =IFERROR(INDEX(tblProjects[Priority],6),"") | E33: =IFERROR(INDEX(tblProjects[Progress %],6),"") | F33: =IFERROR(INDEX(tblProjects[Auto Health],6),"") | G33: =IFERROR(INDEX(tblProjects[Open Issues],6),"") | H33: =IFERROR(INDEX(tblProjects[Open Risks],6),"") | I33: =IFERROR(INDEX(tblProjects[Logged Hours],6),"")
A34: =IFERROR(INDEX(tblProjects[Project ID],7),"") | B34: =IFERROR(INDEX(tblProjects[Project Name],7),"") | C34: =IFERROR(INDEX(tblProjects[Manual Status],7),"") | D34: =IFERROR(INDEX(tblProjects[Priority],7),"") | E34: =IFERROR(INDEX(tblProjects[Progress %],7),"") | F34: =IFERROR(INDEX(tblProjects[Auto Health],7),"") | G34: =IFERROR(INDEX(tblProjects[Open Issues],7),"") | H34: =IFERROR(INDEX(tblProjects[Open Risks],7),"") | I34: =IFERROR(INDEX(tblProjects[Logged Hours],7),"")
A35: =IFERROR(INDEX(tblProjects[Project ID],8),"") | B35: =IFERROR(INDEX(tblProjects[Project Name],8),"") | C35: =IFERROR(INDEX(tblProjects[Manual Status],8),"") | D35: =IFERROR(INDEX(tblProjects[Priority],8),"") | E35: =IFERROR(INDEX(tblProjects[Progress %],8),"") | F35: =IFERROR(INDEX(tblProjects[Auto Health],8),"") | G35: =IFERROR(INDEX(tblProjects[Open Issues],8),"") | H35: =IFERROR(INDEX(tblProjects[Open Risks],8),"") | I35: =IFERROR(INDEX(tblProjects[Logged Hours],8),"")
A36: =IFERROR(INDEX(tblProjects[Project ID],9),"") | B36: =IFERROR(INDEX(tblProjects[Project Name],9),"") | C36: =IFERROR(INDEX(tblProjects[Manual Status],9),"") | D36: =IFERROR(INDEX(tblProjects[Priority],9),"") | E36: =IFERROR(INDEX(tblProjects[Progress %],9),"") | F36: =IFERROR(INDEX(tblProjects[Auto Health],9),"") | G36: =IFERROR(INDEX(tblProjects[Open Issues],9),"") | H36: =IFERROR(INDEX(tblProjects[Open Risks],9),"") | I36: =IFERROR(INDEX(tblProjects[Logged Hours],9),"")
A37: =IFERROR(INDEX(tblProjects[Project ID],10),"") | B37: =IFERROR(INDEX(tblProjects[Project Name],10),"") | C37: =IFERROR(INDEX(tblProjects[Manual Status],10),"") | D37: =IFERROR(INDEX(tblProjects[Priority],10),"") | E37: =IFERROR(INDEX(tblProjects[Progress %],10),"") | F37: =IFERROR(INDEX(tblProjects[Auto Health],10),"") | G37: =IFERROR(INDEX(tblProjects[Open Issues],10),"") | H37: =IFERROR(INDEX(tblProjects[Open Risks],10),"") | I37: =IFERROR(INDEX(tblProjects[Logged Hours],10),"")

Sheet Project_Workspace
A1: Project Workspace
A2: Single-project command center: choose project ID in B5
A3: Home | B3: Dashboard | C3: Workspace | D3: Projects | E3: Tasks | F3: Issues | G3: Timesheets | H3: Reports | I3: Master
A5: Select Project ID | B5: PRJ-001
A7: Project Name | B7: =XLOOKUP($B$5,tblProjects[Project ID],tblProjects[Project Name],"") | D7: Manager | E7: =XLOOKUP($B$5,tblProjects[Project ID],tblProjects[Project Manager],"") | G7: Status | H7: =XLOOKUP($B$5,tblProjects[Project ID],tblProjects[Manual Status],"") | J7: Health | K7: =XLOOKUP($B$5,tblProjects[Project ID],tblProjects[Auto Health],"")
A9: Progress | B9: =XLOOKUP($B$5,tblProjects[Project ID],tblProjects[Progress %],"") | D9: Open Issues | E9: =XLOOKUP($B$5,tblProjects[Project ID],tblProjects[Open Issues],"") | G9: Open Risks | H9: =XLOOKUP($B$5,tblProjects[Project ID],tblProjects[Open Risks],"") | J9: Logged Hours | K9: =XLOOKUP($B$5,tblProjects[Project ID],tblProjects[Logged Hours],"")
A12: Project Task Snapshot
A13: Task ID | B13: Task Name | C13: Owner | D13: Status | E13: Priority | F13: Progress | G13: Health | H13: Due Date
A14: =IFERROR(INDEX(FILTER(tblTasks[Task ID],tblTasks[Project ID]=$B$5),1),"") | B14: =IFERROR(INDEX(FILTER(tblTasks[Task Name],tblTasks[Project ID]=$B$5),1),"") | C14: =IFERROR(INDEX(FILTER(tblTasks[Assigned User],tblTasks[Project ID]=$B$5),1),"") | D14: =IFERROR(INDEX(FILTER(tblTasks[Manual Status],tblTasks[Project ID]=$B$5),1),"") | E14: =IFERROR(INDEX(FILTER(tblTasks[Priority],tblTasks[Project ID]=$B$5),1),"") | F14: =IFERROR(INDEX(FILTER(tblTasks[Progress %],tblTasks[Project ID]=$B$5),1),"") | G14: =IFERROR(INDEX(FILTER(tblTasks[Auto Health],tblTasks[Project ID]=$B$5),1),"") | H14: =IFERROR(INDEX(FILTER(tblTasks[Due Date],tblTasks[Project ID]=$B$5),1),"")
A15: =IFERROR(INDEX(FILTER(tblTasks[Task ID],tblTasks[Project ID]=$B$5),2),"") | B15: =IFERROR(INDEX(FILTER(tblTasks[Task Name],tblTasks[Project ID]=$B$5),2),"") | C15: =IFERROR(INDEX(FILTER(tblTasks[Assigned User],tblTasks[Project ID]=$B$5),2),"") | D15: =IFERROR(INDEX(FILTER(tblTasks[Manual Status],tblTasks[Project ID]=$B$5),2),"") | E15: =IFERROR(INDEX(FILTER(tblTasks[Priority],tblTasks[Project ID]=$B$5),2),"") | F15: =IFERROR(INDEX(FILTER(tblTasks[Progress %],tblTasks[Project ID]=$B$5),2),"") | G15: =IFERROR(INDEX(FILTER(tblTasks[Auto Health],tblTasks[Project ID]=$B$5),2),"") | H15: =IFERROR(INDEX(FILTER(tblTasks[Due Date],tblTasks[Project ID]=$B$5),2),"")
A16: =IFERROR(INDEX(FILTER(tblTasks[Task ID],tblTasks[Project ID]=$B$5),3),"") | B16: =IFERROR(INDEX(FILTER(tblTasks[Task Name],tblTasks[Project ID]=$B$5),3),"") | C16: =IFERROR(INDEX(FILTER(tblTasks[Assigned User],tblTasks[Project ID]=$B$5),3),"") | D16: =IFERROR(INDEX(FILTER(tblTasks[Manual Status],tblTasks[Project ID]=$B$5),3),"") | E16: =IFERROR(INDEX(FILTER(tblTasks[Priority],tblTasks[Project ID]=$B$5),3),"") | F16: =IFERROR(INDEX(FILTER(tblTasks[Progress %],tblTasks[Project ID]=$B$5),3),"") | G16: =IFERROR(INDEX(FILTER(tblTasks[Auto Health],tblTasks[Project ID]=$B$5),3),"") | H16: =IFERROR(INDEX(FILTER(tblTasks[Due Date],tblTasks[Project ID]=$B$5),3),"")
A17: =IFERROR(INDEX(FILTER(tblTasks[Task ID],tblTasks[Project ID]=$B$5),4),"") | B17: =IFERROR(INDEX(FILTER(tblTasks[Task Name],tblTasks[Project ID]=$B$5),4),"") | C17: =IFERROR(INDEX(FILTER(tblTasks[Assigned User],tblTasks[Project ID]=$B$5),4),"") | D17: =IFERROR(INDEX(FILTER(tblTasks[Manual Status],tblTasks[Project ID]=$B$5),4),"") | E17: =IFERROR(INDEX(FILTER(tblTasks[Priority],tblTasks[Project ID]=$B$5),4),"") | F17: =IFERROR(INDEX(FILTER(tblTasks[Progress %],tblTasks[Project ID]=$B$5),4),"") | G17: =IFERROR(INDEX(FILTER(tblTasks[Auto Health],tblTasks[Project ID]=$B$5),4),"") | H17: =IFERROR(INDEX(FILTER(tblTasks[Due Date],tblTasks[Project ID]=$B$5),4),"")
A18: =IFERROR(INDEX(FILTER(tblTasks[Task ID],tblTasks[Project ID]=$B$5),5),"") | B18: =IFERROR(INDEX(FILTER(tblTasks[Task Name],tblTasks[Project ID]=$B$5),5),"") | C18: =IFERROR(INDEX(FILTER(tblTasks[Assigned User],tblTasks[Project ID]=$B$5),5),"") | D18: =IFERROR(INDEX(FILTER(tblTasks[Manual Status],tblTasks[Project ID]=$B$5),5),"") | E18: =IFERROR(INDEX(FILTER(tblTasks[Priority],tblTasks[Project ID]=$B$5),5),"") | F18: =IFERROR(INDEX(FILTER(tblTasks[Progress %],tblTasks[Project ID]=$B$5),5),"") | G18: =IFERROR(INDEX(FILTER(tblTasks[Auto Health],tblTasks[Project ID]=$B$5),5),"") | H18: =IFERROR(INDEX(FILTER(tblTasks[Due Date],tblTasks[Project ID]=$B$5),5),"")
A19: =IFERROR(INDEX(FILTER(tblTasks[Task ID],tblTasks[Project ID]=$B$5),6),"") | B19: =IFERROR(INDEX(FILTER(tblTasks[Task Name],tblTasks[Project ID]=$B$5),6),"") | C19: =IFERROR(INDEX(FILTER(tblTasks[Assigned User],tblTasks[Project ID]=$B$5),6),"") | D19: =IFERROR(INDEX(FILTER(tblTasks[Manual Status],tblTasks[Project ID]=$B$5),6),"") | E19: =IFERROR(INDEX(FILTER(tblTasks[Priority],tblTasks[Project ID]=$B$5),6),"") | F19: =IFERROR(INDEX(FILTER(tblTasks[Progress %],tblTasks[Project ID]=$B$5),6),"") | G19: =IFERROR(INDEX(FILTER(tblTasks[Auto Health],tblTasks[Project ID]=$B$5),6),"") | H19: =IFERROR(INDEX(FILTER(tblTasks[Due Date],tblTasks[Project ID]=$B$5),6),"")
A20: =IFERROR(INDEX(FILTER(tblTasks[Task ID],tblTasks[Project ID]=$B$5),7),"") | B20: =IFERROR(INDEX(FILTER(tblTasks[Task Name],tblTasks[Project ID]=$B$5),7),"") | C20: =IFERROR(INDEX(FILTER(tblTasks[Assigned User],tblTasks[Project ID]=$B$5),7),"") | D20: =IFERROR(INDEX(FILTER(tblTasks[Manual Status],tblTasks[Project ID]=$B$5),7),"") | E20: =IFERROR(INDEX(FILTER(tblTasks[Priority],tblTasks[Project ID]=$B$5),7),"") | F20: =IFERROR(INDEX(FILTER(tblTasks[Progress %],tblTasks[Project ID]=$B$5),7),"") | G20: =IFERROR(INDEX(FILTER(tblTasks[Auto Health],tblTasks[Project ID]=$B$5),7),"") | H20: =IFERROR(INDEX(FILTER(tblTasks[Due Date],tblTasks[Project ID]=$B$5),7),"")
A21: =IFERROR(INDEX(FILTER(tblTasks[Task ID],tblTasks[Project ID]=$B$5),8),"") | B21: =IFERROR(INDEX(FILTER(tblTasks[Task Name],tblTasks[Project ID]=$B$5),8),"") | C21: =IFERROR(INDEX(FILTER(tblTasks[Assigned User],tblTasks[Project ID]=$B$5),8),"") | D21: =IFERROR(INDEX(FILTER(tblTasks[Manual Status],tblTasks[Project ID]=$B$5),8),"") | E21: =IFERROR(INDEX(FILTER(tblTasks[Priority],tblTasks[Project ID]=$B$5),8),"") | F21: =IFERROR(INDEX(FILTER(tblTasks[Progress %],tblTasks[Project ID]=$B$5),8),"") | G21: =IFERROR(INDEX(FILTER(tblTasks[Auto Health],tblTasks[Project ID]=$B$5),8),"") | H21: =IFERROR(INDEX(FILTER(tblTasks[Due Date],tblTasks[Project ID]=$B$5),8),"")
A22: =IFERROR(INDEX(FILTER(tblTasks[Task ID],tblTasks[Project ID]=$B$5),9),"") | B22: =IFERROR(INDEX(FILTER(tblTasks[Task Name],tblTasks[Project ID]=$B$5),9),"") | C22: =IFERROR(INDEX(FILTER(tblTasks[Assigned User],tblTasks[Project ID]=$B$5),9),"") | D22: =IFERROR(INDEX(FILTER(tblTasks[Manual Status],tblTasks[Project ID]=$B$5),9),"") | E22: =IFERROR(INDEX(FILTER(tblTasks[Priority],tblTasks[Project ID]=$B$5),9),"") | F22: =IFERROR(INDEX(FILTER(tblTasks[Progress %],tblTasks[Project ID]=$B$5),9),"") | G22: =IFERROR(INDEX(FILTER(tblTasks[Auto Health],tblTasks[Project ID]=$B$5),9),"") | H22: =IFERROR(INDEX(FILTER(tblTasks[Due Date],tblTasks[Project ID]=$B$5),9),"")
A23: =IFERROR(INDEX(FILTER(tblTasks[Task ID],tblTasks[Project ID]=$B$5),10),"") | B23: =IFERROR(INDEX(FILTER(tblTasks[Task Name],tblTasks[Project ID]=$B$5),10),"") | C23: =IFERROR(INDEX(FILTER(tblTasks[Assigned User],tblTasks[Project ID]=$B$5),10),"") | D23: =IFERROR(INDEX(FILTER(tblTasks[Manual Status],tblTasks[Project ID]=$B$5),10),"") | E23: =IFERROR(INDEX(FILTER(tblTasks[Priority],tblTasks[Project ID]=$B$5),10),"") | F23: =IFERROR(INDEX(FILTER(tblTasks[Progress %],tblTasks[Project ID]=$B$5),10),"") | G23: =IFERROR(INDEX(FILTER(tblTasks[Auto Health],tblTasks[Project ID]=$B$5),10),"") | H23: =IFERROR(INDEX(FILTER(tblTasks[Due Date],tblTasks[Project ID]=$B$5),10),"")
A24: =IFERROR(INDEX(FILTER(tblTasks[Task ID],tblTasks[Project ID]=$B$5),11),"") | B24: =IFERROR(INDEX(FILTER(tblTasks[Task Name],tblTasks[Project ID]=$B$5),11),"") | C24: =IFERROR(INDEX(FILTER(tblTasks[Assigned User],tblTasks[Project ID]=$B$5),11),"") | D24: =IFERROR(INDEX(FILTER(tblTasks[Manual Status],tblTasks[Project ID]=$B$5),11),"") | E24: =IFERROR(INDEX(FILTER(tblTasks[Priority],tblTasks[Project ID]=$B$5),11),"") | F24: =IFERROR(INDEX(FILTER(tblTasks[Progress %],tblTasks[Project ID]=$B$5),11),"") | G24: =IFERROR(INDEX(FILTER(tblTasks[Auto Health],tblTasks[Project ID]=$B$5),11),"") | H24: =IFERROR(INDEX(FILTER(tblTasks[Due Date],tblTasks[Project ID]=$B$5),11),"")
A25: =IFERROR(INDEX(FILTER(tblTasks[Task ID],tblTasks[Project ID]=$B$5),12),"") | B25: =IFERROR(INDEX(FILTER(tblTasks[Task Name],tblTasks[Project ID]=$B$5),12),"") | C25: =IFERROR(INDEX(FILTER(tblTasks[Assigned User],tblTasks[Project ID]=$B$5),12),"") | D25: =IFERROR(INDEX(FILTER(tblTasks[Manual Status],tblTasks[Project ID]=$B$5),12),"") | E25: =IFERROR(INDEX(FILTER(tblTasks[Priority],tblTasks[Project ID]=$B$5),12),"") | F25: =IFERROR(INDEX(FILTER(tblTasks[Progress %],tblTasks[Project ID]=$B$5),12),"") | G25: =IFERROR(INDEX(FILTER(tblTasks[Auto Health],tblTasks[Project ID]=$B$5),12),"") | H25: =IFERROR(INDEX(FILTER(tblTasks[Due Date],tblTasks[Project ID]=$B$5),12),"")
A26: =IFERROR(INDEX(FILTER(tblTasks[Task ID],tblTasks[Project ID]=$B$5),13),"") | B26: =IFERROR(INDEX(FILTER(tblTasks[Task Name],tblTasks[Project ID]=$B$5),13),"") | C26: =IFERROR(INDEX(FILTER(tblTasks[Assigned User],tblTasks[Project ID]=$B$5),13),"") | D26: =IFERROR(INDEX(FILTER(tblTasks[Manual Status],tblTasks[Project ID]=$B$5),13),"") | E26: =IFERROR(INDEX(FILTER(tblTasks[Priority],tblTasks[Project ID]=$B$5),13),"") | F26: =IFERROR(INDEX(FILTER(tblTasks[Progress %],tblTasks[Project ID]=$B$5),13),"") | G26: =IFERROR(INDEX(FILTER(tblTasks[Auto Health],tblTasks[Project ID]=$B$5),13),"") | H26: =IFERROR(INDEX(FILTER(tblTasks[Due Date],tblTasks[Project ID]=$B$5),13),"")
A27: =IFERROR(INDEX(FILTER(tblTasks[Task ID],tblTasks[Project ID]=$B$5),14),"") | B27: =IFERROR(INDEX(FILTER(tblTasks[Task Name],tblTasks[Project ID]=$B$5),14),"") | C27: =IFERROR(INDEX(FILTER(tblTasks[Assigned User],tblTasks[Project ID]=$B$5),14),"") | D27: =IFERROR(INDEX(FILTER(tblTasks[Manual Status],tblTasks[Project ID]=$B$5),14),"") | E27: =IFERROR(INDEX(FILTER(tblTasks[Priority],tblTasks[Project ID]=$B$5),14),"") | F27: =IFERROR(INDEX(FILTER(tblTasks[Progress %],tblTasks[Project ID]=$B$5),14),"") | G27: =IFERROR(INDEX(FILTER(tblTasks[Auto Health],tblTasks[Project ID]=$B$5),14),"") | H27: =IFERROR(INDEX(FILTER(tblTasks[Due Date],tblTasks[Project ID]=$B$5),14),"")
A28: =IFERROR(INDEX(FILTER(tblTasks[Task ID],tblTasks[Project ID]=$B$5),15),"") | B28: =IFERROR(INDEX(FILTER(tblTasks[Task Name],tblTasks[Project ID]=$B$5),15),"") | C28: =IFERROR(INDEX(FILTER(tblTasks[Assigned User],tblTasks[Project ID]=$B$5),15),"") | D28: =IFERROR(INDEX(FILTER(tblTasks[Manual Status],tblTasks[Project ID]=$B$5),15),"") | E28: =IFERROR(INDEX(FILTER(tblTasks[Priority],tblTasks[Project ID]=$B$5),15),"") | F28: =IFERROR(INDEX(FILTER(tblTasks[Progress %],tblTasks[Project ID]=$B$5),15),"") | G28: =IFERROR(INDEX(FILTER(tblTasks[Auto Health],tblTasks[Project ID]=$B$5),15),"") | H28: =IFERROR(INDEX(FILTER(tblTasks[Due Date],tblTasks[Project ID]=$B$5),15),"")
A31: Recent Activity
A32: Date | B32: Type | C32: User | D32: Task | E32: Comment
A33: =IFERROR(INDEX(FILTER(tblActivity[Activity Date],tblActivity[Project ID]=$B$5),1),"") | B33: =IFERROR(INDEX(FILTER(tblActivity[Activity Type],tblActivity[Project ID]=$B$5),1),"") | C33: =IFERROR(INDEX(FILTER(tblActivity[User ID],tblActivity[Project ID]=$B$5),1),"") | D33: =IFERROR(INDEX(FILTER(tblActivity[Task ID],tblActivity[Project ID]=$B$5),1),"") | E33: =IFERROR(INDEX(FILTER(tblActivity[Comment / Update],tblActivity[Project ID]=$B$5),1),"")
A34: =IFERROR(INDEX(FILTER(tblActivity[Activity Date],tblActivity[Project ID]=$B$5),2),"") | B34: =IFERROR(INDEX(FILTER(tblActivity[Activity Type],tblActivity[Project ID]=$B$5),2),"") | C34: =IFERROR(INDEX(FILTER(tblActivity[User ID],tblActivity[Project ID]=$B$5),2),"") | D34: =IFERROR(INDEX(FILTER(tblActivity[Task ID],tblActivity[Project ID]=$B$5),2),"") | E34: =IFERROR(INDEX(FILTER(tblActivity[Comment / Update],tblActivity[Project ID]=$B$5),2),"")
A35: =IFERROR(INDEX(FILTER(tblActivity[Activity Date],tblActivity[Project ID]=$B$5),3),"") | B35: =IFERROR(INDEX(FILTER(tblActivity[Activity Type],tblActivity[Project ID]=$B$5),3),"") | C35: =IFERROR(INDEX(FILTER(tblActivity[User ID],tblActivity[Project ID]=$B$5),3),"") | D35: =IFERROR(INDEX(FILTER(tblActivity[Task ID],tblActivity[Project ID]=$B$5),3),"") | E35: =IFERROR(INDEX(FILTER(tblActivity[Comment / Update],tblActivity[Project ID]=$B$5),3),"")
A36: =IFERROR(INDEX(FILTER(tblActivity[Activity Date],tblActivity[Project ID]=$B$5),4),"") | B36: =IFERROR(INDEX(FILTER(tblActivity[Activity Type],tblActivity[Project ID]=$B$5),4),"") | C36: =IFERROR(INDEX(FILTER(tblActivity[User ID],tblActivity[Project ID]=$B$5),4),"") | D36: =IFERROR(INDEX(FILTER(tblActivity[Task ID],tblActivity[Project ID]=$B$5),4),"") | E36: =IFERROR(INDEX(FILTER(tblActivity[Comment / Update],tblActivity[Project ID]=$B$5),4),"")
A37: =IFERROR(INDEX(FILTER(tblActivity[Activity Date],tblActivity[Project ID]=$B$5),5),"") | B37: =IFERROR(INDEX(FILTER(tblActivity[Activity Type],tblActivity[Project ID]=$B$5),5),"") | C37: =IFERROR(INDEX(FILTER(tblActivity[User ID],tblActivity[Project ID]=$B$5),5),"") | D37: =IFERROR(INDEX(FILTER(tblActivity[Task ID],tblActivity[Project ID]=$B$5),5),"") | E37: =IFERROR(INDEX(FILTER(tblActivity[Comment / Update],tblActivity[Project ID]=$B$5),5),"")
A38: =IFERROR(INDEX(FILTER(tblActivity[Activity Date],tblActivity[Project ID]=$B$5),6),"") | B38: =IFERROR(INDEX(FILTER(tblActivity[Activity Type],tblActivity[Project ID]=$B$5),6),"") | C38: =IFERROR(INDEX(FILTER(tblActivity[User ID],tblActivity[Project ID]=$B$5),6),"") | D38: =IFERROR(INDEX(FILTER(tblActivity[Task ID],tblActivity[Project ID]=$B$5),6),"") | E38: =IFERROR(INDEX(FILTER(tblActivity[Comment / Update],tblActivity[Project ID]=$B$5),6),"")
A39: =IFERROR(INDEX(FILTER(tblActivity[Activity Date],tblActivity[Project ID]=$B$5),7),"") | B39: =IFERROR(INDEX(FILTER(tblActivity[Activity Type],tblActivity[Project ID]=$B$5),7),"") | C39: =IFERROR(INDEX(FILTER(tblActivity[User ID],tblActivity[Project ID]=$B$5),7),"") | D39: =IFERROR(INDEX(FILTER(tblActivity[Task ID],tblActivity[Project ID]=$B$5),7),"") | E39: =IFERROR(INDEX(FILTER(tblActivity[Comment / Update],tblActivity[Project ID]=$B$5),7),"")
A40: =IFERROR(INDEX(FILTER(tblActivity[Activity Date],tblActivity[Project ID]=$B$5),8),"") | B40: =IFERROR(INDEX(FILTER(tblActivity[Activity Type],tblActivity[Project ID]=$B$5),8),"") | C40: =IFERROR(INDEX(FILTER(tblActivity[User ID],tblActivity[Project ID]=$B$5),8),"") | D40: =IFERROR(INDEX(FILTER(tblActivity[Task ID],tblActivity[Project ID]=$B$5),8),"") | E40: =IFERROR(INDEX(FILTER(tblActivity[Comment / Update],tblActivity[Project ID]=$B$5),8),"")
A41: =IFERROR(INDEX(FILTER(tblActivity[Activity Date],tblActivity[Project ID]=$B$5),9),"") | B41: =IFERROR(INDEX(FILTER(tblActivity[Activity Type],tblActivity[Project ID]=$B$5),9),"") | C41: =IFERROR(INDEX(FILTER(tblActivity[User ID],tblActivity[Project ID]=$B$5),9),"") | D41: =IFERROR(INDEX(FILTER(tblActivity[Task ID],tblActivity[Project ID]=$B$5),9),"") | E41: =IFERROR(INDEX(FILTER(tblActivity[Comment / Update],tblActivity[Project ID]=$B$5),9),"")

Sheet Projects
A1: Projects
A2: Multi-project portfolio master
A3: Home | B3: Dashboard | C3: Workspace | D3: Projects | E3: Tasks | F3: Issues | G3: Timesheets | H3: Reports | I3: Master
A5: Project ID | B5: Project Name | C5: Client ID | D5: Team ID | E5: Project Manager | F5: Start Date | G5: End Date | H5: Manual Status | I5: Priority | J5: Budget | K5: Actual Cost | L5: Task Count | M5: Completed Tasks | N5: Open Issues | O5: Open Risks | P5: Logged Hours | Q5: Progress % | R5: Auto Health | S5: Days Remaining | T5: Project Group | U5: Notes
A6: PRJ-001 | B6: ERP Modernization | C6: CL-001 | D6: TEAM-001 | E6: USR-001 | F6: 46142 | G6: 46232 | H6: In Progress | I6: Critical | J6: 750000 | K6: 280000 | L6: =COUNTIF(tblTasks[Project ID],[@[Project ID]]) | M6: =COUNTIFS(tblTasks[Project ID],[@[Project ID]],tblTasks[Manual Status],"Completed") | N6: =COUNTIFS(tblIssues[Project ID],[@[Project ID]],tblIssues[Status],"<>Closed",tblIssues[Status],"<>Resolved") | O6: =COUNTIFS(tblRisks[Project ID],[@[Project ID]],tblRisks[Status],"<>Closed") | P6: =SUMIF(tblTimesheets[Project ID],[@[Project ID]],tblTimesheets[Hours]) | Q6: =IFERROR([@[Completed Tasks]]/[@[Task Count]],0) | R6: =IF([@[Manual Status]]="Completed","Completed",IF(COUNTIFS(tblTasks[Project ID],[@[Project ID]],tblTasks[Auto Health],"Overdue")>0,"Overdue",IF(COUNTIFS(tblTasks[Project ID],[@[Project ID]],tblTasks[Auto Health],"At Risk")>0,"At Risk",IF(COUNTIFS(tblTasks[Project ID],[@[Project ID]],tblTasks[Manual Status],"Blocked")>0,"Blocked",IF([@[Task Count]]=0,"Not Started","On Track"))))) | S6: =MAX(0,[@[End Date]]-TODAY()) | T6: Strategic | U6: Core ERP transformation
A7: PRJ-002 | B7: Customer Portal | C7: CL-002 | D7: TEAM-001 | E7: USR-001 | F7: 46162 | G7: 46217 | H7: In Progress | I7: High | J7: 320000 | K7: 85000 | L7: =COUNTIF(tblTasks[Project ID],[@[Project ID]]) | M7: =COUNTIFS(tblTasks[Project ID],[@[Project ID]],tblTasks[Manual Status],"Completed") | N7: =COUNTIFS(tblIssues[Project ID],[@[Project ID]],tblIssues[Status],"<>Closed",tblIssues[Status],"<>Resolved") | O7: =COUNTIFS(tblRisks[Project ID],[@[Project ID]],tblRisks[Status],"<>Closed") | P7: =SUMIF(tblTimesheets[Project ID],[@[Project ID]],tblTimesheets[Hours]) | Q7: =IFERROR([@[Completed Tasks]]/[@[Task Count]],0) | R7: =IF([@[Manual Status]]="Completed","Completed",IF(COUNTIFS(tblTasks[Project ID],[@[Project ID]],tblTasks[Auto Health],"Overdue")>0,"Overdue",IF(COUNTIFS(tblTasks[Project ID],[@[Project ID]],tblTasks[Auto Health],"At Risk")>0,"At Risk",IF(COUNTIFS(tblTasks[Project ID],[@[Project ID]],tblTasks[Manual Status],"Blocked")>0,"Blocked",IF([@[Task Count]]=0,"Not Started","On Track"))))) | S7: =MAX(0,[@[End Date]]-TODAY()) | T7: Customer Experience | U7: Self-service portal
A8: PRJ-003 | B8: Data Quality Program | C8: CL-003 | D8: TEAM-002 | E8: USR-004 | F8: 46117 | G8: 46202 | H8: Planning | I8: Medium | J8: 150000 | K8: 45000 | L8: =COUNTIF(tblTasks[Project ID],[@[Project ID]]) | M8: =COUNTIFS(tblTasks[Project ID],[@[Project ID]],tblTasks[Manual Status],"Completed") | N8: =COUNTIFS(tblIssues[Project ID],[@[Project ID]],tblIssues[Status],"<>Closed",tblIssues[Status],"<>Resolved") | O8: =COUNTIFS(tblRisks[Project ID],[@[Project ID]],tblRisks[Status],"<>Closed") | P8: =SUMIF(tblTimesheets[Project ID],[@[Project ID]],tblTimesheets[Hours]) | Q8: =IFERROR([@[Completed Tasks]]/[@[Task Count]],0) | R8: =IF([@[Manual Status]]="Completed","Completed",IF(COUNTIFS(tblTasks[Project ID],[@[Project ID]],tblTasks[Auto Health],"Overdue")>0,"Overdue",IF(COUNTIFS(tblTasks[Project ID],[@[Project ID]],tblTasks[Auto Health],"At Risk")>0,"At Risk",IF(COUNTIFS(tblTasks[Project ID],[@[Project ID]],tblTasks[Manual Status],"Blocked")>0,"Blocked",IF([@[Task Count]]=0,"Not Started","On Track"))))) | S8: =MAX(0,[@[End Date]]-TODAY()) | T8: Governance | U8: Data quality remediation
A9: PRJ-004 | B9: Branch Ops Automation | C9: CL-004 | D9: TEAM-003 | E9: USR-005 | F9: 46172 | G9: 46252 | H9: Not Started | I9: High | J9: 410000 | K9: 20000 | L9: =COUNTIF(tblTasks[Project ID],[@[Project ID]]) | M9: =COUNTIFS(tblTasks[Project ID],[@[Project ID]],tblTasks[Manual Status],"Completed") | N9: =COUNTIFS(tblIssues[Project ID],[@[Project ID]],tblIssues[Status],"<>Closed",tblIssues[Status],"<>Resolved") | O9: =COUNTIFS(tblRisks[Project ID],[@[Project ID]],tblRisks[Status],"<>Closed") | P9: =SUMIF(tblTimesheets[Project ID],[@[Project ID]],tblTimesheets[Hours]) | Q9: =IFERROR([@[Completed Tasks]]/[@[Task Count]],0) | R9: =IF([@[Manual Status]]="Completed","Completed",IF(COUNTIFS(tblTasks[Project ID],[@[Project ID]],tblTasks[Auto Health],"Overdue")>0,"Overdue",IF(COUNTIFS(tblTasks[Project ID],[@[Project ID]],tblTasks[Auto Health],"At Risk")>0,"At Risk",IF(COUNTIFS(tblTasks[Project ID],[@[Project ID]],tblTasks[Manual Status],"Blocked")>0,"Blocked",IF([@[Task Count]]=0,"Not Started","On Track"))))) | S9: =MAX(0,[@[End Date]]-TODAY()) | T9: Automation | U9: Workflow automation
A10: PRJ-005 | B10: Mobile App Refresh | C10: CL-002 | D10: TEAM-001 | E10: USR-003 | F10: 46092 | G10: 46177 | H10: Completed | I10: Medium | J10: 180000 | K10: 175000 | L10: =COUNTIF(tblTasks[Project ID],[@[Project ID]]) | M10: =COUNTIFS(tblTasks[Project ID],[@[Project ID]],tblTasks[Manual Status],"Completed") | N10: =COUNTIFS(tblIssues[Project ID],[@[Project ID]],tblIssues[Status],"<>Closed",tblIssues[Status],"<>Resolved") | O10: =COUNTIFS(tblRisks[Project ID],[@[Project ID]],tblRisks[Status],"<>Closed") | P10: =SUMIF(tblTimesheets[Project ID],[@[Project ID]],tblTimesheets[Hours]) | Q10: =IFERROR([@[Completed Tasks]]/[@[Task Count]],0) | R10: =IF([@[Manual Status]]="Completed","Completed",IF(COUNTIFS(tblTasks[Project ID],[@[Project ID]],tblTasks[Auto Health],"Overdue")>0,"Overdue",IF(COUNTIFS(tblTasks[Project ID],[@[Project ID]],tblTasks[Auto Health],"At Risk")>0,"At Risk",IF(COUNTIFS(tblTasks[Project ID],[@[Project ID]],tblTasks[Manual Status],"Blocked")>0,"Blocked",IF([@[Task Count]]=0,"Not Started","On Track"))))) | S10: =MAX(0,[@[End Date]]-TODAY()) | T10: Experience | U10: Mobile UX refresh

Sheet Tasks
A1: Tasks
A2: Project-aware task list with dependencies and health
A3: Home | B3: Dashboard | C3: Workspace | D3: Projects | E3: Tasks | F3: Issues | G3: Timesheets | H3: Reports | I3: Master
A5: Task ID | B5: Project ID | C5: Task Name | D5: Category | E5: Assigned User | F5: Start Date | G5: Due Date | H5: Manual Status | I5: Priority | J5: Progress % | K5: Depends On Task ID | L5: Blocked? | M5: Blocking Reason | N5: Sprint / Phase | O5: Subtask Count | P5: Completed Subtasks | Q5: Issue Count | R5: Logged Hours | S5: Auto Health | T5: Days Late | U5: Notes
A6: TSK-001 | B6: PRJ-001 | C6: Requirements workshop | D6: Requirement | E6: USR-001 | F6: 46147 | G6: 46162 | H6: Completed | I6: High | J6: 1 | L6: No | N6: Sprint 1 | O6: =COUNTIF(tblSubtasks[Parent Task ID],[@[Task ID]]) | P6: =COUNTIFS(tblSubtasks[Parent Task ID],[@[Task ID]],tblSubtasks[Manual Status],"Completed") | Q6: =COUNTIFS(tblIssues[Task ID],[@[Task ID]],tblIssues[Status],"<>Closed",tblIssues[Status],"<>Resolved") | R6: =SUMIF(tblTimesheets[Task ID],[@[Task ID]],tblTimesheets[Hours]) | S6: =IF([@[Manual Status]]="Completed","Completed",IF([@[Manual Status]]="Blocked","Blocked",IF(AND([@[Due Date]]<TODAY(),[@[Manual Status]]<>"Completed",[@[Manual Status]]<>"Cancelled"),"Overdue",IF(AND([@[Due Date]]-TODAY()<=3,[@[Progress %]]<0.8),"At Risk",IF([@[Progress %]]=0,"Not Started","On Track"))))) | T6: =IF(AND([@[Due Date]]<TODAY(),[@[Manual Status]]<>"Completed"),TODAY()-[@[Due Date]],0)
A7: TSK-002 | B7: PRJ-001 | C7: Integration design | D7: Design | E7: USR-003 | F7: 46164 | G7: 46187 | H7: In Progress | I7: Critical | J7: 0.65 | K7: TSK-001 | L7: No | N7: Sprint 2 | O7: =COUNTIF(tblSubtasks[Parent Task ID],[@[Task ID]]) | P7: =COUNTIFS(tblSubtasks[Parent Task ID],[@[Task ID]],tblSubtasks[Manual Status],"Completed") | Q7: =COUNTIFS(tblIssues[Task ID],[@[Task ID]],tblIssues[Status],"<>Closed",tblIssues[Status],"<>Resolved") | R7: =SUMIF(tblTimesheets[Task ID],[@[Task ID]],tblTimesheets[Hours]) | S7: =IF([@[Manual Status]]="Completed","Completed",IF([@[Manual Status]]="Blocked","Blocked",IF(AND([@[Due Date]]<TODAY(),[@[Manual Status]]<>"Completed",[@[Manual Status]]<>"Cancelled"),"Overdue",IF(AND([@[Due Date]]-TODAY()<=3,[@[Progress %]]<0.8),"At Risk",IF([@[Progress %]]=0,"Not Started","On Track"))))) | T7: =IF(AND([@[Due Date]]<TODAY(),[@[Manual Status]]<>"Completed"),TODAY()-[@[Due Date]],0)
A8: TSK-003 | B8: PRJ-001 | C8: Build Oracle connector | D8: Development | E8: USR-002 | F8: 46176 | G8: 46200 | H8: In Progress | I8: Critical | J8: 0.32 | K8: TSK-002 | L8: No | N8: Sprint 2 | O8: =COUNTIF(tblSubtasks[Parent Task ID],[@[Task ID]]) | P8: =COUNTIFS(tblSubtasks[Parent Task ID],[@[Task ID]],tblSubtasks[Manual Status],"Completed") | Q8: =COUNTIFS(tblIssues[Task ID],[@[Task ID]],tblIssues[Status],"<>Closed",tblIssues[Status],"<>Resolved") | R8: =SUMIF(tblTimesheets[Task ID],[@[Task ID]],tblTimesheets[Hours]) | S8: =IF([@[Manual Status]]="Completed","Completed",IF([@[Manual Status]]="Blocked","Blocked",IF(AND([@[Due Date]]<TODAY(),[@[Manual Status]]<>"Completed",[@[Manual Status]]<>"Cancelled"),"Overdue",IF(AND([@[Due Date]]-TODAY()<=3,[@[Progress %]]<0.8),"At Risk",IF([@[Progress %]]=0,"Not Started","On Track"))))) | T8: =IF(AND([@[Due Date]]<TODAY(),[@[Manual Status]]<>"Completed"),TODAY()-[@[Due Date]],0)
A9: TSK-004 | B9: PRJ-002 | C9: Portal wireframes | D9: Design | E9: USR-003 | F9: 46167 | G9: 46180 | H9: Completed | I9: High | J9: 1 | L9: No | N9: Sprint 1 | O9: =COUNTIF(tblSubtasks[Parent Task ID],[@[Task ID]]) | P9: =COUNTIFS(tblSubtasks[Parent Task ID],[@[Task ID]],tblSubtasks[Manual Status],"Completed") | Q9: =COUNTIFS(tblIssues[Task ID],[@[Task ID]],tblIssues[Status],"<>Closed",tblIssues[Status],"<>Resolved") | R9: =SUMIF(tblTimesheets[Task ID],[@[Task ID]],tblTimesheets[Hours]) | S9: =IF([@[Manual Status]]="Completed","Completed",IF([@[Manual Status]]="Blocked","Blocked",IF(AND([@[Due Date]]<TODAY(),[@[Manual Status]]<>"Completed",[@[Manual Status]]<>"Cancelled"),"Overdue",IF(AND([@[Due Date]]-TODAY()<=3,[@[Progress %]]<0.8),"At Risk",IF([@[Progress %]]=0,"Not Started","On Track"))))) | T9: =IF(AND([@[Due Date]]<TODAY(),[@[Manual Status]]<>"Completed"),TODAY()-[@[Due Date]],0)
A10: TSK-005 | B10: PRJ-002 | C10: Authentication module | D10: Development | E10: USR-002 | F10: 46174 | G10: 46204 | H10: Blocked | I10: High | J10: 0.2 | K10: TSK-004 | L10: Yes | M10: Security review pending | N10: Sprint 2 | O10: =COUNTIF(tblSubtasks[Parent Task ID],[@[Task ID]]) | P10: =COUNTIFS(tblSubtasks[Parent Task ID],[@[Task ID]],tblSubtasks[Manual Status],"Completed") | Q10: =COUNTIFS(tblIssues[Task ID],[@[Task ID]],tblIssues[Status],"<>Closed",tblIssues[Status],"<>Resolved") | R10: =SUMIF(tblTimesheets[Task ID],[@[Task ID]],tblTimesheets[Hours]) | S10: =IF([@[Manual Status]]="Completed","Completed",IF([@[Manual Status]]="Blocked","Blocked",IF(AND([@[Due Date]]<TODAY(),[@[Manual Status]]<>"Completed",[@[Manual Status]]<>"Cancelled"),"Overdue",IF(AND([@[Due Date]]-TODAY()<=3,[@[Progress %]]<0.8),"At Risk",IF([@[Progress %]]=0,"Not Started","On Track"))))) | T10: =IF(AND([@[Due Date]]<TODAY(),[@[Manual Status]]<>"Completed"),TODAY()-[@[Due Date]],0)
A11: TSK-006 | B11: PRJ-003 | C11: Data profiling | D11: Research | E11: USR-004 | F11: 46127 | G11: 46174 | H11: In Progress | I11: Medium | J11: 0.7 | L11: No | N11: Phase 1 | O11: =COUNTIF(tblSubtasks[Parent Task ID],[@[Task ID]]) | P11: =COUNTIFS(tblSubtasks[Parent Task ID],[@[Task ID]],tblSubtasks[Manual Status],"Completed") | Q11: =COUNTIFS(tblIssues[Task ID],[@[Task ID]],tblIssues[Status],"<>Closed",tblIssues[Status],"<>Resolved") | R11: =SUMIF(tblTimesheets[Task ID],[@[Task ID]],tblTimesheets[Hours]) | S11: =IF([@[Manual Status]]="Completed","Completed",IF([@[Manual Status]]="Blocked","Blocked",IF(AND([@[Due Date]]<TODAY(),[@[Manual Status]]<>"Completed",[@[Manual Status]]<>"Cancelled"),"Overdue",IF(AND([@[Due Date]]-TODAY()<=3,[@[Progress %]]<0.8),"At Risk",IF([@[Progress %]]=0,"Not Started","On Track"))))) | T11: =IF(AND([@[Due Date]]<TODAY(),[@[Manual Status]]<>"Completed"),TODAY()-[@[Due Date]],0)
A12: TSK-007 | B12: PRJ-003 | C12: Remediation plan | D12: Documentation | E12: USR-006 | F12: 46177 | G12: 46192 | H12: Not Started | I12: Medium | J12: 0 | K12: TSK-006 | L12: No | N12: Phase 1 | O12: =COUNTIF(tblSubtasks[Parent Task ID],[@[Task ID]]) | P12: =COUNTIFS(tblSubtasks[Parent Task ID],[@[Task ID]],tblSubtasks[Manual Status],"Completed") | Q12: =COUNTIFS(tblIssues[Task ID],[@[Task ID]],tblIssues[Status],"<>Closed",tblIssues[Status],"<>Resolved") | R12: =SUMIF(tblTimesheets[Task ID],[@[Task ID]],tblTimesheets[Hours]) | S12: =IF([@[Manual Status]]="Completed","Completed",IF([@[Manual Status]]="Blocked","Blocked",IF(AND([@[Due Date]]<TODAY(),[@[Manual Status]]<>"Completed",[@[Manual Status]]<>"Cancelled"),"Overdue",IF(AND([@[Due Date]]-TODAY()<=3,[@[Progress %]]<0.8),"At Risk",IF([@[Progress %]]=0,"Not Started","On Track"))))) | T12: =IF(AND([@[Due Date]]<TODAY(),[@[Manual Status]]<>"Completed"),TODAY()-[@[Due Date]],0)
A13: TSK-008 | B13: PRJ-004 | C13: Workflow mapping | D13: Requirement | E13: USR-006 | F13: 46178 | G13: 46194 | H13: In Progress | I13: High | J13: 0.35 | L13: No | N13: Discovery | O13: =COUNTIF(tblSubtasks[Parent Task ID],[@[Task ID]]) | P13: =COUNTIFS(tblSubtasks[Parent Task ID],[@[Task ID]],tblSubtasks[Manual Status],"Completed") | Q13: =COUNTIFS(tblIssues[Task ID],[@[Task ID]],tblIssues[Status],"<>Closed",tblIssues[Status],"<>Resolved") | R13: =SUMIF(tblTimesheets[Task ID],[@[Task ID]],tblTimesheets[Hours]) | S13: =IF([@[Manual Status]]="Completed","Completed",IF([@[Manual Status]]="Blocked","Blocked",IF(AND([@[Due Date]]<TODAY(),[@[Manual Status]]<>"Completed",[@[Manual Status]]<>"Cancelled"),"Overdue",IF(AND([@[Due Date]]-TODAY()<=3,[@[Progress %]]<0.8),"At Risk",IF([@[Progress %]]=0,"Not Started","On Track"))))) | T13: =IF(AND([@[Due Date]]<TODAY(),[@[Manual Status]]<>"Completed"),TODAY()-[@[Due Date]],0)
A14: TSK-009 | B14: PRJ-004 | C14: Pilot deployment | D14: Deployment | E14: USR-005 | F14: 46192 | G14: 46227 | H14: Not Started | I14: High | J14: 0 | K14: TSK-008 | L14: No | N14: Pilot | O14: =COUNTIF(tblSubtasks[Parent Task ID],[@[Task ID]]) | P14: =COUNTIFS(tblSubtasks[Parent Task ID],[@[Task ID]],tblSubtasks[Manual Status],"Completed") | Q14: =COUNTIFS(tblIssues[Task ID],[@[Task ID]],tblIssues[Status],"<>Closed",tblIssues[Status],"<>Resolved") | R14: =SUMIF(tblTimesheets[Task ID],[@[Task ID]],tblTimesheets[Hours]) | S14: =IF([@[Manual Status]]="Completed","Completed",IF([@[Manual Status]]="Blocked","Blocked",IF(AND([@[Due Date]]<TODAY(),[@[Manual Status]]<>"Completed",[@[Manual Status]]<>"Cancelled"),"Overdue",IF(AND([@[Due Date]]-TODAY()<=3,[@[Progress %]]<0.8),"At Risk",IF([@[Progress %]]=0,"Not Started","On Track"))))) | T14: =IF(AND([@[Due Date]]<TODAY(),[@[Manual Status]]<>"Completed"),TODAY()-[@[Due Date]],0)
A15: TSK-010 | B15: PRJ-005 | C15: Release closure | D15: Deployment | E15: USR-005 | F15: 46162 | G15: 46177 | H15: Completed | I15: Medium | J15: 1 | L15: No | N15: Closure | O15: =COUNTIF(tblSubtasks[Parent Task ID],[@[Task ID]]) | P15: =COUNTIFS(tblSubtasks[Parent Task ID],[@[Task ID]],tblSubtasks[Manual Status],"Completed") | Q15: =COUNTIFS(tblIssues[Task ID],[@[Task ID]],tblIssues[Status],"<>Closed",tblIssues[Status],"<>Resolved") | R15: =SUMIF(tblTimesheets[Task ID],[@[Task ID]],tblTimesheets[Hours]) | S15: =IF([@[Manual Status]]="Completed","Completed",IF([@[Manual Status]]="Blocked","Blocked",IF(AND([@[Due Date]]<TODAY(),[@[Manual Status]]<>"Completed",[@[Manual Status]]<>"Cancelled"),"Overdue",IF(AND([@[Due Date]]-TODAY()<=3,[@[Progress %]]<0.8),"At Risk",IF([@[Progress %]]=0,"Not Started","On Track"))))) | T15: =IF(AND([@[Due Date]]<TODAY(),[@[Manual Status]]<>"Completed"),TODAY()-[@[Due Date]],0)

Sheet Subtasks
A1: Subtasks
A2: Detailed execution checklist
A3: Home | B3: Dashboard | C3: Workspace | D3: Projects | E3: Tasks | F3: Issues | G3: Timesheets | H3: Reports | I3: Master
A5: Subtask ID | B5: Parent Task ID | C5: Project ID | D5: Subtask Name | E5: Assigned User | F5: Due Date | G5: Manual Status | H5: Priority | I5: Completion % | J5: Auto Health | K5: Days Late
A6: SUB-001 | B6: TSK-002 | C6: PRJ-001 | D6: Interface inventory | E6: USR-003 | F6: 46184 | G6: In Progress | H6: High | I6: 0.7 | J6: =IF([@[Manual Status]]="Completed","Completed",IF(AND([@[Due Date]]<TODAY(),[@[Manual Status]]<>"Completed"),"Overdue",IF(AND([@[Due Date]]-TODAY()<=3,[@[Completion %]]<0.8),"At Risk",IF([@[Completion %]]=0,"Not Started","On Track")))) | K6: =IF(AND([@[Due Date]]<TODAY(),[@[Manual Status]]<>"Completed"),TODAY()-[@[Due Date]],0)
A7: SUB-002 | B7: TSK-003 | C7: PRJ-001 | D7: Connection pool | E7: USR-002 | F7: 46190 | G7: Not Started | H7: Critical | I7: 0 | J7: =IF([@[Manual Status]]="Completed","Completed",IF(AND([@[Due Date]]<TODAY(),[@[Manual Status]]<>"Completed"),"Overdue",IF(AND([@[Due Date]]-TODAY()<=3,[@[Completion %]]<0.8),"At Risk",IF([@[Completion %]]=0,"Not Started","On Track")))) | K7: =IF(AND([@[Due Date]]<TODAY(),[@[Manual Status]]<>"Completed"),TODAY()-[@[Due Date]],0)
A8: SUB-003 | B8: TSK-005 | C8: PRJ-002 | D8: SSO spike | E8: USR-002 | F8: 46188 | G8: Blocked | H8: High | I8: 0.15 | J8: =IF([@[Manual Status]]="Completed","Completed",IF(AND([@[Due Date]]<TODAY(),[@[Manual Status]]<>"Completed"),"Overdue",IF(AND([@[Due Date]]-TODAY()<=3,[@[Completion %]]<0.8),"At Risk",IF([@[Completion %]]=0,"Not Started","On Track")))) | K8: =IF(AND([@[Due Date]]<TODAY(),[@[Manual Status]]<>"Completed"),TODAY()-[@[Due Date]],0)
A9: SUB-004 | B9: TSK-006 | C9: PRJ-003 | D9: Profile customer table | E9: USR-004 | F9: 46178 | G9: In Progress | H9: Medium | I9: 0.8 | J9: =IF([@[Manual Status]]="Completed","Completed",IF(AND([@[Due Date]]<TODAY(),[@[Manual Status]]<>"Completed"),"Overdue",IF(AND([@[Due Date]]-TODAY()<=3,[@[Completion %]]<0.8),"At Risk",IF([@[Completion %]]=0,"Not Started","On Track")))) | K9: =IF(AND([@[Due Date]]<TODAY(),[@[Manual Status]]<>"Completed"),TODAY()-[@[Due Date]],0)
A10: SUB-005 | B10: TSK-008 | C10: PRJ-004 | D10: Current-state process map | E10: USR-006 | F10: 46187 | G10: In Progress | H10: High | I10: 0.45 | J10: =IF([@[Manual Status]]="Completed","Completed",IF(AND([@[Due Date]]<TODAY(),[@[Manual Status]]<>"Completed"),"Overdue",IF(AND([@[Due Date]]-TODAY()<=3,[@[Completion %]]<0.8),"At Risk",IF([@[Completion %]]=0,"Not Started","On Track")))) | K10: =IF(AND([@[Due Date]]<TODAY(),[@[Manual Status]]<>"Completed"),TODAY()-[@[Due Date]],0)

Sheet Milestones
A1: Milestones
A2: Major checkpoints and delivery gates
A3: Home | B3: Dashboard | C3: Workspace | D3: Projects | E3: Tasks | F3: Issues | G3: Timesheets | H3: Reports | I3: Master
A5: Milestone ID | B5: Project ID | C5: Milestone Name | D5: Owner | E5: Target Date | F5: Manual Status | G5: Priority | H5: Auto Health | I5: Days Remaining
A6: MS-001 | B6: PRJ-001 | C6: Architecture sign-off | D6: USR-001 | E6: 46194 | F6: In Progress | G6: Critical | H6: =IF([@[Manual Status]]="Completed","Completed",IF(AND([@[Target Date]]<TODAY(),[@[Manual Status]]<>"Completed"),"Overdue",IF([@[Target Date]]-TODAY()<=5,"At Risk","On Track"))) | I6: =MAX(0,[@[Target Date]]-TODAY())
A7: MS-002 | B7: PRJ-002 | C7: Portal beta | D7: USR-001 | E7: 46207 | F7: Not Started | G7: High | H7: =IF([@[Manual Status]]="Completed","Completed",IF(AND([@[Target Date]]<TODAY(),[@[Manual Status]]<>"Completed"),"Overdue",IF([@[Target Date]]-TODAY()<=5,"At Risk","On Track"))) | I7: =MAX(0,[@[Target Date]]-TODAY())
A8: MS-003 | B8: PRJ-003 | C8: DQ baseline approved | D8: USR-004 | E8: 46186 | F8: In Progress | G8: Medium | H8: =IF([@[Manual Status]]="Completed","Completed",IF(AND([@[Target Date]]<TODAY(),[@[Manual Status]]<>"Completed"),"Overdue",IF([@[Target Date]]-TODAY()<=5,"At Risk","On Track"))) | I8: =MAX(0,[@[Target Date]]-TODAY())
A9: MS-004 | B9: PRJ-004 | C9: Pilot go-live | D9: USR-005 | E9: 46232 | F9: Not Started | G9: High | H9: =IF([@[Manual Status]]="Completed","Completed",IF(AND([@[Target Date]]<TODAY(),[@[Manual Status]]<>"Completed"),"Overdue",IF([@[Target Date]]-TODAY()<=5,"At Risk","On Track"))) | I9: =MAX(0,[@[Target Date]]-TODAY())
A10: MS-005 | B10: PRJ-005 | C10: Closure accepted | D10: USR-001 | E10: 46179 | F10: Completed | G10: Medium | H10: =IF([@[Manual Status]]="Completed","Completed",IF(AND([@[Target Date]]<TODAY(),[@[Manual Status]]<>"Completed"),"Overdue",IF([@[Target Date]]-TODAY()<=5,"At Risk","On Track"))) | I10: =MAX(0,[@[Target Date]]-TODAY())

Sheet Issues
A1: Issues
A2: Zoho-style issue and blocker register
A3: Home | B3: Dashboard | C3: Workspace | D3: Projects | E3: Tasks | F3: Issues | G3: Timesheets | H3: Reports | I3: Master
A5: Issue ID | B5: Project ID | C5: Task ID | D5: Type | E5: Title | F5: Owner | G5: Priority | H5: Status | I5: Created Date | J5: Due Date | K5: Age Days | L5: Auto Health | M5: Notes
A6: ISS-001 | B6: PRJ-001 | C6: TSK-003 | D6: Dependency | E6: Oracle access delay | F6: USR-002 | G6: High | H6: In Progress | I6: 46180 | J6: 46185 | K6: =TODAY()-[@[Created Date]] | L6: =IF([@[Status]]="Closed","Completed",IF([@[Status]]="Resolved","Completed",IF(AND([@[Due Date]]<TODAY(),[@[Status]]<>"Closed",[@[Status]]<>"Resolved"),"Overdue",IF([@[Priority]]="Critical","At Risk","On Track")))) | M6: Need DBA approval
A7: ISS-002 | B7: PRJ-002 | C7: TSK-005 | D7: Blocker | E7: Security sign-off pending | F7: USR-001 | G7: Critical | H7: Open | I7: 46177 | J7: 46183 | K7: =TODAY()-[@[Created Date]] | L7: =IF([@[Status]]="Closed","Completed",IF([@[Status]]="Resolved","Completed",IF(AND([@[Due Date]]<TODAY(),[@[Status]]<>"Closed",[@[Status]]<>"Resolved"),"Overdue",IF([@[Priority]]="Critical","At Risk","On Track")))) | M7: Escalated to security
A8: ISS-003 | B8: PRJ-003 | C8: TSK-006 | D8: Bug | E8: Missing source ownership | F8: USR-004 | G8: Medium | H8: Waiting | I8: 46172 | J8: 46188 | K8: =TODAY()-[@[Created Date]] | L8: =IF([@[Status]]="Closed","Completed",IF([@[Status]]="Resolved","Completed",IF(AND([@[Due Date]]<TODAY(),[@[Status]]<>"Closed",[@[Status]]<>"Resolved"),"Overdue",IF([@[Priority]]="Critical","At Risk","On Track")))) | M8: Waiting data steward
A9: ISS-004 | B9: PRJ-004 | C9: TSK-008 | D9: Change Request | E9: Add approval workflow | F9: USR-006 | G9: Medium | H9: Open | I9: 46181 | J9: 46196 | K9: =TODAY()-[@[Created Date]] | L9: =IF([@[Status]]="Closed","Completed",IF([@[Status]]="Resolved","Completed",IF(AND([@[Due Date]]<TODAY(),[@[Status]]<>"Closed",[@[Status]]<>"Resolved"),"Overdue",IF([@[Priority]]="Critical","At Risk","On Track")))) | M9: Scope review

Sheet Risks
A1: Risks
A2: Risk register with mitigation tracking
A3: Home | B3: Dashboard | C3: Workspace | D3: Projects | E3: Tasks | F3: Issues | G3: Timesheets | H3: Reports | I3: Master
A5: Risk ID | B5: Project ID | C5: Risk Title | D5: Owner | E5: Probability | F5: Impact | G5: Severity | H5: Mitigation | I5: Status | J5: Risk Score
A6: RSK-001 | B6: PRJ-001 | C6: Legacy schema unknowns | D6: USR-002 | E6: High | F6: Medium | G6: High | H6: Run profiling spike | I6: Mitigating | J6: =IF([@[Severity]]="Critical",9,IF([@[Severity]]="High",6,IF([@[Severity]]="Medium",3,1)))
A7: RSK-002 | B7: PRJ-002 | C7: Security approval may slip | D7: USR-001 | E7: High | F7: High | G7: Critical | H7: Escalate weekly | I7: Escalated | J7: =IF([@[Severity]]="Critical",9,IF([@[Severity]]="High",6,IF([@[Severity]]="Medium",3,1)))
A8: RSK-003 | B8: PRJ-003 | C8: Low business owner availability | D8: USR-004 | E8: Medium | F8: High | G8: Medium | H8: Set governance cadence | I8: Open | J8: =IF([@[Severity]]="Critical",9,IF([@[Severity]]="High",6,IF([@[Severity]]="Medium",3,1)))
A9: RSK-004 | B9: PRJ-004 | C9: Pilot adoption risk | D9: USR-005 | E9: Medium | F9: Medium | G9: Medium | H9: Training and hypercare | I9: Open | J9: =IF([@[Severity]]="Critical",9,IF([@[Severity]]="High",6,IF([@[Severity]]="Medium",3,1)))

Sheet Timesheets
A1: Timesheets
A2: Project and task time tracking
A3: Home | B3: Dashboard | C3: Workspace | D3: Projects | E3: Tasks | F3: Issues | G3: Timesheets | H3: Reports | I3: Master
A5: Entry ID | B5: Project ID | C5: Task ID | D5: User ID | E5: Work Date | F5: Hours | G5: Billable | H5: Work Description
A6: TIME-001 | B6: PRJ-001 | C6: TSK-002 | D6: USR-003 | E6: 46181 | F6: 6 | G6: Billable | H6: Design review
A7: TIME-002 | B7: PRJ-001 | C7: TSK-003 | D7: USR-002 | E7: 46181 | F7: 7 | G7: Billable | H7: Connector build
A8: TIME-003 | B8: PRJ-002 | C8: TSK-005 | D8: USR-002 | E8: 46180 | F8: 5 | G8: Billable | H8: Auth spike
A9: TIME-004 | B9: PRJ-003 | C9: TSK-006 | D9: USR-004 | E9: 46179 | F9: 4 | G9: Non-Billable | H9: Data profiling
A10: TIME-005 | B10: PRJ-004 | C10: TSK-008 | D10: USR-006 | E10: 46182 | F10: 6 | G10: Billable | H10: Workshop notes

Sheet Calendar
A1: Calendar
A2: Upcoming due dates across all projects
A3: Home | B3: Dashboard | C3: Workspace | D3: Projects | E3: Tasks | F3: Issues | G3: Timesheets | H3: Reports | I3: Master
A5: Item Type | B5: Project ID | C5: Item ID | D5: Title | E5: Owner | F5: Due Date | G5: Status | H5: Health
A6: Task | B6: =IFERROR(INDEX(tblTasks[Project ID],1),"") | C6: =IFERROR(INDEX(tblTasks[Task ID],1),"") | D6: =IFERROR(INDEX(tblTasks[Task Name],1),"") | E6: =IFERROR(INDEX(tblTasks[Assigned User],1),"") | F6: =IFERROR(INDEX(tblTasks[Due Date],1),"") | G6: =IFERROR(INDEX(tblTasks[Manual Status],1),"") | H6: =IFERROR(INDEX(tblTasks[Auto Health],1),"")
A7: Task | B7: =IFERROR(INDEX(tblTasks[Project ID],2),"") | C7: =IFERROR(INDEX(tblTasks[Task ID],2),"") | D7: =IFERROR(INDEX(tblTasks[Task Name],2),"") | E7: =IFERROR(INDEX(tblTasks[Assigned User],2),"") | F7: =IFERROR(INDEX(tblTasks[Due Date],2),"") | G7: =IFERROR(INDEX(tblTasks[Manual Status],2),"") | H7: =IFERROR(INDEX(tblTasks[Auto Health],2),"")
A8: Task | B8: =IFERROR(INDEX(tblTasks[Project ID],3),"") | C8: =IFERROR(INDEX(tblTasks[Task ID],3),"") | D8: =IFERROR(INDEX(tblTasks[Task Name],3),"") | E8: =IFERROR(INDEX(tblTasks[Assigned User],3),"") | F8: =IFERROR(INDEX(tblTasks[Due Date],3),"") | G8: =IFERROR(INDEX(tblTasks[Manual Status],3),"") | H8: =IFERROR(INDEX(tblTasks[Auto Health],3),"")
A9: Task | B9: =IFERROR(INDEX(tblTasks[Project ID],4),"") | C9: =IFERROR(INDEX(tblTasks[Task ID],4),"") | D9: =IFERROR(INDEX(tblTasks[Task Name],4),"") | E9: =IFERROR(INDEX(tblTasks[Assigned User],4),"") | F9: =IFERROR(INDEX(tblTasks[Due Date],4),"") | G9: =IFERROR(INDEX(tblTasks[Manual Status],4),"") | H9: =IFERROR(INDEX(tblTasks[Auto Health],4),"")
A10: Task | B10: =IFERROR(INDEX(tblTasks[Project ID],5),"") | C10: =IFERROR(INDEX(tblTasks[Task ID],5),"") | D10: =IFERROR(INDEX(tblTasks[Task Name],5),"") | E10: =IFERROR(INDEX(tblTasks[Assigned User],5),"") | F10: =IFERROR(INDEX(tblTasks[Due Date],5),"") | G10: =IFERROR(INDEX(tblTasks[Manual Status],5),"") | H10: =IFERROR(INDEX(tblTasks[Auto Health],5),"")
A11: Task | B11: =IFERROR(INDEX(tblTasks[Project ID],6),"") | C11: =IFERROR(INDEX(tblTasks[Task ID],6),"") | D11: =IFERROR(INDEX(tblTasks[Task Name],6),"") | E11: =IFERROR(INDEX(tblTasks[Assigned User],6),"") | F11: =IFERROR(INDEX(tblTasks[Due Date],6),"") | G11: =IFERROR(INDEX(tblTasks[Manual Status],6),"") | H11: =IFERROR(INDEX(tblTasks[Auto Health],6),"")
A12: Task | B12: =IFERROR(INDEX(tblTasks[Project ID],7),"") | C12: =IFERROR(INDEX(tblTasks[Task ID],7),"") | D12: =IFERROR(INDEX(tblTasks[Task Name],7),"") | E12: =IFERROR(INDEX(tblTasks[Assigned User],7),"") | F12: =IFERROR(INDEX(tblTasks[Due Date],7),"") | G12: =IFERROR(INDEX(tblTasks[Manual Status],7),"") | H12: =IFERROR(INDEX(tblTasks[Auto Health],7),"")
A13: Task | B13: =IFERROR(INDEX(tblTasks[Project ID],8),"") | C13: =IFERROR(INDEX(tblTasks[Task ID],8),"") | D13: =IFERROR(INDEX(tblTasks[Task Name],8),"") | E13: =IFERROR(INDEX(tblTasks[Assigned User],8),"") | F13: =IFERROR(INDEX(tblTasks[Due Date],8),"") | G13: =IFERROR(INDEX(tblTasks[Manual Status],8),"") | H13: =IFERROR(INDEX(tblTasks[Auto Health],8),"")
A14: Task | B14: =IFERROR(INDEX(tblTasks[Project ID],9),"") | C14: =IFERROR(INDEX(tblTasks[Task ID],9),"") | D14: =IFERROR(INDEX(tblTasks[Task Name],9),"") | E14: =IFERROR(INDEX(tblTasks[Assigned User],9),"") | F14: =IFERROR(INDEX(tblTasks[Due Date],9),"") | G14: =IFERROR(INDEX(tblTasks[Manual Status],9),"") | H14: =IFERROR(INDEX(tblTasks[Auto Health],9),"")
A15: Task | B15: =IFERROR(INDEX(tblTasks[Project ID],10),"") | C15: =IFERROR(INDEX(tblTasks[Task ID],10),"") | D15: =IFERROR(INDEX(tblTasks[Task Name],10),"") | E15: =IFERROR(INDEX(tblTasks[Assigned User],10),"") | F15: =IFERROR(INDEX(tblTasks[Due Date],10),"") | G15: =IFERROR(INDEX(tblTasks[Manual Status],10),"") | H15: =IFERROR(INDEX(tblTasks[Auto Health],10),"")
A16: Task | B16: =IFERROR(INDEX(tblTasks[Project ID],11),"") | C16: =IFERROR(INDEX(tblTasks[Task ID],11),"") | D16: =IFERROR(INDEX(tblTasks[Task Name],11),"") | E16: =IFERROR(INDEX(tblTasks[Assigned User],11),"") | F16: =IFERROR(INDEX(tblTasks[Due Date],11),"") | G16: =IFERROR(INDEX(tblTasks[Manual Status],11),"") | H16: =IFERROR(INDEX(tblTasks[Auto Health],11),"")
A17: Task | B17: =IFERROR(INDEX(tblTasks[Project ID],12),"") | C17: =IFERROR(INDEX(tblTasks[Task ID],12),"") | D17: =IFERROR(INDEX(tblTasks[Task Name],12),"") | E17: =IFERROR(INDEX(tblTasks[Assigned User],12),"") | F17: =IFERROR(INDEX(tblTasks[Due Date],12),"") | G17: =IFERROR(INDEX(tblTasks[Manual Status],12),"") | H17: =IFERROR(INDEX(tblTasks[Auto Health],12),"")
A18: Task | B18: =IFERROR(INDEX(tblTasks[Project ID],13),"") | C18: =IFERROR(INDEX(tblTasks[Task ID],13),"") | D18: =IFERROR(INDEX(tblTasks[Task Name],13),"") | E18: =IFERROR(INDEX(tblTasks[Assigned User],13),"") | F18: =IFERROR(INDEX(tblTasks[Due Date],13),"") | G18: =IFERROR(INDEX(tblTasks[Manual Status],13),"") | H18: =IFERROR(INDEX(tblTasks[Auto Health],13),"")
A19: Task | B19: =IFERROR(INDEX(tblTasks[Project ID],14),"") | C19: =IFERROR(INDEX(tblTasks[Task ID],14),"") | D19: =IFERROR(INDEX(tblTasks[Task Name],14),"") | E19: =IFERROR(INDEX(tblTasks[Assigned User],14),"") | F19: =IFERROR(INDEX(tblTasks[Due Date],14),"") | G19: =IFERROR(INDEX(tblTasks[Manual Status],14),"") | H19: =IFERROR(INDEX(tblTasks[Auto Health],14),"")
A20: Task | B20: =IFERROR(INDEX(tblTasks[Project ID],15),"") | C20: =IFERROR(INDEX(tblTasks[Task ID],15),"") | D20: =IFERROR(INDEX(tblTasks[Task Name],15),"") | E20: =IFERROR(INDEX(tblTasks[Assigned User],15),"") | F20: =IFERROR(INDEX(tblTasks[Due Date],15),"") | G20: =IFERROR(INDEX(tblTasks[Manual Status],15),"") | H20: =IFERROR(INDEX(tblTasks[Auto Health],15),"")
A21: Task | B21: =IFERROR(INDEX(tblTasks[Project ID],16),"") | C21: =IFERROR(INDEX(tblTasks[Task ID],16),"") | D21: =IFERROR(INDEX(tblTasks[Task Name],16),"") | E21: =IFERROR(INDEX(tblTasks[Assigned User],16),"") | F21: =IFERROR(INDEX(tblTasks[Due Date],16),"") | G21: =IFERROR(INDEX(tblTasks[Manual Status],16),"") | H21: =IFERROR(INDEX(tblTasks[Auto Health],16),"")
A22: Task | B22: =IFERROR(INDEX(tblTasks[Project ID],17),"") | C22: =IFERROR(INDEX(tblTasks[Task ID],17),"") | D22: =IFERROR(INDEX(tblTasks[Task Name],17),"") | E22: =IFERROR(INDEX(tblTasks[Assigned User],17),"") | F22: =IFERROR(INDEX(tblTasks[Due Date],17),"") | G22: =IFERROR(INDEX(tblTasks[Manual Status],17),"") | H22: =IFERROR(INDEX(tblTasks[Auto Health],17),"")
A23: Task | B23: =IFERROR(INDEX(tblTasks[Project ID],18),"") | C23: =IFERROR(INDEX(tblTasks[Task ID],18),"") | D23: =IFERROR(INDEX(tblTasks[Task Name],18),"") | E23: =IFERROR(INDEX(tblTasks[Assigned User],18),"") | F23: =IFERROR(INDEX(tblTasks[Due Date],18),"") | G23: =IFERROR(INDEX(tblTasks[Manual Status],18),"") | H23: =IFERROR(INDEX(tblTasks[Auto Health],18),"")
A24: Task | B24: =IFERROR(INDEX(tblTasks[Project ID],19),"") | C24: =IFERROR(INDEX(tblTasks[Task ID],19),"") | D24: =IFERROR(INDEX(tblTasks[Task Name],19),"") | E24: =IFERROR(INDEX(tblTasks[Assigned User],19),"") | F24: =IFERROR(INDEX(tblTasks[Due Date],19),"") | G24: =IFERROR(INDEX(tblTasks[Manual Status],19),"") | H24: =IFERROR(INDEX(tblTasks[Auto Health],19),"")
A25: Task | B25: =IFERROR(INDEX(tblTasks[Project ID],20),"") | C25: =IFERROR(INDEX(tblTasks[Task ID],20),"") | D25: =IFERROR(INDEX(tblTasks[Task Name],20),"") | E25: =IFERROR(INDEX(tblTasks[Assigned User],20),"") | F25: =IFERROR(INDEX(tblTasks[Due Date],20),"") | G25: =IFERROR(INDEX(tblTasks[Manual Status],20),"") | H25: =IFERROR(INDEX(tblTasks[Auto Health],20),"")

Sheet Kanban_View
A1: Kanban View
A2: Status board-style task view
A3: Home | B3: Dashboard | C3: Workspace | D3: Projects | E3: Tasks | F3: Issues | G3: Timesheets | H3: Reports | I3: Master
A5: Not Started | B5: In Progress | C5: Blocked | D5: In Review | E5: Completed
A6: =IFERROR(INDEX(FILTER(tblTasks[Task Name],tblTasks[Manual Status]=A$5),1),"") | B6: =IFERROR(INDEX(FILTER(tblTasks[Task Name],tblTasks[Manual Status]=B$5),1),"") | C6: =IFERROR(INDEX(FILTER(tblTasks[Task Name],tblTasks[Manual Status]=C$5),1),"") | D6: =IFERROR(INDEX(FILTER(tblTasks[Task Name],tblTasks[Manual Status]=D$5),1),"") | E6: =IFERROR(INDEX(FILTER(tblTasks[Task Name],tblTasks[Manual Status]=E$5),1),"")
A7: =IFERROR(INDEX(FILTER(tblTasks[Task Name],tblTasks[Manual Status]=A$5),2),"") | B7: =IFERROR(INDEX(FILTER(tblTasks[Task Name],tblTasks[Manual Status]=B$5),2),"") | C7: =IFERROR(INDEX(FILTER(tblTasks[Task Name],tblTasks[Manual Status]=C$5),2),"") | D7: =IFERROR(INDEX(FILTER(tblTasks[Task Name],tblTasks[Manual Status]=D$5),2),"") | E7: =IFERROR(INDEX(FILTER(tblTasks[Task Name],tblTasks[Manual Status]=E$5),2),"")
A8: =IFERROR(INDEX(FILTER(tblTasks[Task Name],tblTasks[Manual Status]=A$5),3),"") | B8: =IFERROR(INDEX(FILTER(tblTasks[Task Name],tblTasks[Manual Status]=B$5),3),"") | C8: =IFERROR(INDEX(FILTER(tblTasks[Task Name],tblTasks[Manual Status]=C$5),3),"") | D8: =IFERROR(INDEX(FILTER(tblTasks[Task Name],tblTasks[Manual Status]=D$5),3),"") | E8: =IFERROR(INDEX(FILTER(tblTasks[Task Name],tblTasks[Manual Status]=E$5),3),"")
A9: =IFERROR(INDEX(FILTER(tblTasks[Task Name],tblTasks[Manual Status]=A$5),4),"") | B9: =IFERROR(INDEX(FILTER(tblTasks[Task Name],tblTasks[Manual Status]=B$5),4),"") | C9: =IFERROR(INDEX(FILTER(tblTasks[Task Name],tblTasks[Manual Status]=C$5),4),"") | D9: =IFERROR(INDEX(FILTER(tblTasks[Task Name],tblTasks[Manual Status]=D$5),4),"") | E9: =IFERROR(INDEX(FILTER(tblTasks[Task Name],tblTasks[Manual Status]=E$5),4),"")
A10: =IFERROR(INDEX(FILTER(tblTasks[Task Name],tblTasks[Manual Status]=A$5),5),"") | B10: =IFERROR(INDEX(FILTER(tblTasks[Task Name],tblTasks[Manual Status]=B$5),5),"") | C10: =IFERROR(INDEX(FILTER(tblTasks[Task Name],tblTasks[Manual Status]=C$5),5),"") | D10: =IFERROR(INDEX(FILTER(tblTasks[Task Name],tblTasks[Manual Status]=D$5),5),"") | E10: =IFERROR(INDEX(FILTER(tblTasks[Task Name],tblTasks[Manual Status]=E$5),5),"")
A11: =IFERROR(INDEX(FILTER(tblTasks[Task Name],tblTasks[Manual Status]=A$5),6),"") | B11: =IFERROR(INDEX(FILTER(tblTasks[Task Name],tblTasks[Manual Status]=B$5),6),"") | C11: =IFERROR(INDEX(FILTER(tblTasks[Task Name],tblTasks[Manual Status]=C$5),6),"") | D11: =IFERROR(INDEX(FILTER(tblTasks[Task Name],tblTasks[Manual Status]=D$5),6),"") | E11: =IFERROR(INDEX(FILTER(tblTasks[Task Name],tblTasks[Manual Status]=E$5),6),"")
A12: =IFERROR(INDEX(FILTER(tblTasks[Task Name],tblTasks[Manual Status]=A$5),7),"") | B12: =IFERROR(INDEX(FILTER(tblTasks[Task Name],tblTasks[Manual Status]=B$5),7),"") | C12: =IFERROR(INDEX(FILTER(tblTasks[Task Name],tblTasks[Manual Status]=C$5),7),"") | D12: =IFERROR(INDEX(FILTER(tblTasks[Task Name],tblTasks[Manual Status]=D$5),7),"") | E12: =IFERROR(INDEX(FILTER(tblTasks[Task Name],tblTasks[Manual Status]=E$5),7),"")
A13: =IFERROR(INDEX(FILTER(tblTasks[Task Name],tblTasks[Manual Status]=A$5),8),"") | B13: =IFERROR(INDEX(FILTER(tblTasks[Task Name],tblTasks[Manual Status]=B$5),8),"") | C13: =IFERROR(INDEX(FILTER(tblTasks[Task Name],tblTasks[Manual Status]=C$5),8),"") | D13: =IFERROR(INDEX(FILTER(tblTasks[Task Name],tblTasks[Manual Status]=D$5),8),"") | E13: =IFERROR(INDEX(FILTER(tblTasks[Task Name],tblTasks[Manual Status]=E$5),8),"")
A14: =IFERROR(INDEX(FILTER(tblTasks[Task Name],tblTasks[Manual Status]=A$5),9),"") | B14: =IFERROR(INDEX(FILTER(tblTasks[Task Name],tblTasks[Manual Status]=B$5),9),"") | C14: =IFERROR(INDEX(FILTER(tblTasks[Task Name],tblTasks[Manual Status]=C$5),9),"") | D14: =IFERROR(INDEX(FILTER(tblTasks[Task Name],tblTasks[Manual Status]=D$5),9),"") | E14: =IFERROR(INDEX(FILTER(tblTasks[Task Name],tblTasks[Manual Status]=E$5),9),"")
A15: =IFERROR(INDEX(FILTER(tblTasks[Task Name],tblTasks[Manual Status]=A$5),10),"") | B15: =IFERROR(INDEX(FILTER(tblTasks[Task Name],tblTasks[Manual Status]=B$5),10),"") | C15: =IFERROR(INDEX(FILTER(tblTasks[Task Name],tblTasks[Manual Status]=C$5),10),"") | D15: =IFERROR(INDEX(FILTER(tblTasks[Task Name],tblTasks[Manual Status]=D$5),10),"") | E15: =IFERROR(INDEX(FILTER(tblTasks[Task Name],tblTasks[Manual Status]=E$5),10),"")
A16: =IFERROR(INDEX(FILTER(tblTasks[Task Name],tblTasks[Manual Status]=A$5),11),"") | B16: =IFERROR(INDEX(FILTER(tblTasks[Task Name],tblTasks[Manual Status]=B$5),11),"") | C16: =IFERROR(INDEX(FILTER(tblTasks[Task Name],tblTasks[Manual Status]=C$5),11),"") | D16: =IFERROR(INDEX(FILTER(tblTasks[Task Name],tblTasks[Manual Status]=D$5),11),"") | E16: =IFERROR(INDEX(FILTER(tblTasks[Task Name],tblTasks[Manual Status]=E$5),11),"")
A17: =IFERROR(INDEX(FILTER(tblTasks[Task Name],tblTasks[Manual Status]=A$5),12),"") | B17: =IFERROR(INDEX(FILTER(tblTasks[Task Name],tblTasks[Manual Status]=B$5),12),"") | C17: =IFERROR(INDEX(FILTER(tblTasks[Task Name],tblTasks[Manual Status]=C$5),12),"") | D17: =IFERROR(INDEX(FILTER(tblTasks[Task Name],tblTasks[Manual Status]=D$5),12),"") | E17: =IFERROR(INDEX(FILTER(tblTasks[Task Name],tblTasks[Manual Status]=E$5),12),"")
A18: =IFERROR(INDEX(FILTER(tblTasks[Task Name],tblTasks[Manual Status]=A$5),13),"") | B18: =IFERROR(INDEX(FILTER(tblTasks[Task Name],tblTasks[Manual Status]=B$5),13),"") | C18: =IFERROR(INDEX(FILTER(tblTasks[Task Name],tblTasks[Manual Status]=C$5),13),"") | D18: =IFERROR(INDEX(FILTER(tblTasks[Task Name],tblTasks[Manual Status]=D$5),13),"") | E18: =IFERROR(INDEX(FILTER(tblTasks[Task Name],tblTasks[Manual Status]=E$5),13),"")
A19: =IFERROR(INDEX(FILTER(tblTasks[Task Name],tblTasks[Manual Status]=A$5),14),"") | B19: =IFERROR(INDEX(FILTER(tblTasks[Task Name],tblTasks[Manual Status]=B$5),14),"") | C19: =IFERROR(INDEX(FILTER(tblTasks[Task Name],tblTasks[Manual Status]=C$5),14),"") | D19: =IFERROR(INDEX(FILTER(tblTasks[Task Name],tblTasks[Manual Status]=D$5),14),"") | E19: =IFERROR(INDEX(FILTER(tblTasks[Task Name],tblTasks[Manual Status]=E$5),14),"")
A20: =IFERROR(INDEX(FILTER(tblTasks[Task Name],tblTasks[Manual Status]=A$5),15),"") | B20: =IFERROR(INDEX(FILTER(tblTasks[Task Name],tblTasks[Manual Status]=B$5),15),"") | C20: =IFERROR(INDEX(FILTER(tblTasks[Task Name],tblTasks[Manual Status]=C$5),15),"") | D20: =IFERROR(INDEX(FILTER(tblTasks[Task Name],tblTasks[Manual Status]=D$5),15),"") | E20: =IFERROR(INDEX(FILTER(tblTasks[Task Name],tblTasks[Manual Status]=E$5),15),"")

Sheet Activity_Log
A1: Activity Log
A2: Project activity stream and comments
A3: Home | B3: Dashboard | C3: Workspace | D3: Projects | E3: Tasks | F3: Issues | G3: Timesheets | H3: Reports | I3: Master
A5: Activity ID | B5: Project ID | C5: Task ID | D5: Activity Type | E5: User ID | F5: Activity Date | G5: Comment / Update
A6: ACT-001 | B6: PRJ-001 | C6: TSK-003 | D6: Comment | E6: USR-002 | F6: 46181 | G6: Connector design shared for review
A7: ACT-002 | B7: PRJ-002 | C7: TSK-005 | D7: Escalation | E7: USR-001 | F7: 46181 | G7: Security review escalated
A8: ACT-003 | B8: PRJ-003 | C8: TSK-006 | D8: Status Change | E8: USR-004 | F8: 46180 | G8: Profiling moved to in progress
A9: ACT-004 | B9: PRJ-004 | C9: TSK-008 | D9: Meeting | E9: USR-006 | F9: 46182 | G9: Workflow discovery meeting completed

Sheet Documents
A1: Documents
A2: Document and file reference register
A3: Home | B3: Dashboard | C3: Workspace | D3: Projects | E3: Tasks | F3: Issues | G3: Timesheets | H3: Reports | I3: Master
A5: Document ID | B5: Project ID | C5: Document Type | D5: Document Name | E5: Owner | F5: Upload Date | G5: Link / Location
A6: DOC-001 | B6: PRJ-001 | C6: BRD | D6: ERP requirements | E6: USR-001 | F6: 46152 | G6: SharePoint/ERP-BRD
A7: DOC-002 | B7: PRJ-002 | C7: Design | D7: Portal wireframes | E7: USR-003 | F7: 46175 | G7: Figma/Portal
A8: DOC-003 | B8: PRJ-003 | C8: Report | D8: DQ baseline | E8: USR-004 | F8: 46179 | G8: Drive/DQ
A9: DOC-004 | B9: PRJ-004 | C9: Minutes | D9: Workshop notes | E9: USR-006 | F9: 46182 | G9: Drive/Ops

Sheet Users
A1: Users
A2: Resource directory and calculated workload
A3: Home | B3: Dashboard | C3: Workspace | D3: Projects | E3: Tasks | F3: Issues | G3: Timesheets | H3: Reports | I3: Master
A5: User ID | B5: Full Name | C5: Email | D5: Department | E5: Role | F5: Availability | G5: Capacity Hours/Week | H5: Assigned Tasks | I5: Active Tasks | J5: Overdue Tasks | K5: Logged Hours | L5: Utilization %
A6: USR-001 | B6: Aarav Sharma | C6: aarav@example.com | D6: PMO | E6: Project Manager | F6: Available | G6: 40 | H6: =COUNTIF(tblTasks[Assigned User],[@[User ID]]) | I6: =COUNTIFS(tblTasks[Assigned User],[@[User ID]],tblTasks[Manual Status],"<>Completed",tblTasks[Manual Status],"<>Cancelled") | J6: =COUNTIFS(tblTasks[Assigned User],[@[User ID]],tblTasks[Auto Health],"Overdue") | K6: =SUMIF(tblTimesheets[User ID],[@[User ID]],tblTimesheets[Hours]) | L6: =IFERROR([@[Logged Hours]]/([@[Capacity Hours/Week]]*4),0)
A7: USR-002 | B7: Meera Iyer | C7: meera@example.com | D7: Engineering | E7: Developer | F7: Busy | G7: 40 | H7: =COUNTIF(tblTasks[Assigned User],[@[User ID]]) | I7: =COUNTIFS(tblTasks[Assigned User],[@[User ID]],tblTasks[Manual Status],"<>Completed",tblTasks[Manual Status],"<>Cancelled") | J7: =COUNTIFS(tblTasks[Assigned User],[@[User ID]],tblTasks[Auto Health],"Overdue") | K7: =SUMIF(tblTimesheets[User ID],[@[User ID]],tblTimesheets[Hours]) | L7: =IFERROR([@[Logged Hours]]/([@[Capacity Hours/Week]]*4),0)
A8: USR-003 | B8: Rohan Gupta | C8: rohan@example.com | D8: Design | E8: Designer | F8: Available | G8: 35 | H8: =COUNTIF(tblTasks[Assigned User],[@[User ID]]) | I8: =COUNTIFS(tblTasks[Assigned User],[@[User ID]],tblTasks[Manual Status],"<>Completed",tblTasks[Manual Status],"<>Cancelled") | J8: =COUNTIFS(tblTasks[Assigned User],[@[User ID]],tblTasks[Auto Health],"Overdue") | K8: =SUMIF(tblTimesheets[User ID],[@[User ID]],tblTimesheets[Hours]) | L8: =IFERROR([@[Logged Hours]]/([@[Capacity Hours/Week]]*4),0)
A9: USR-004 | B9: Nisha Rao | C9: nisha@example.com | D9: QA | E9: QA Engineer | F9: Available | G9: 40 | H9: =COUNTIF(tblTasks[Assigned User],[@[User ID]]) | I9: =COUNTIFS(tblTasks[Assigned User],[@[User ID]],tblTasks[Manual Status],"<>Completed",tblTasks[Manual Status],"<>Cancelled") | J9: =COUNTIFS(tblTasks[Assigned User],[@[User ID]],tblTasks[Auto Health],"Overdue") | K9: =SUMIF(tblTimesheets[User ID],[@[User ID]],tblTimesheets[Hours]) | L9: =IFERROR([@[Logged Hours]]/([@[Capacity Hours/Week]]*4),0)
A10: USR-005 | B10: Vikram Menon | C10: vikram@example.com | D10: Operations | E10: DevOps | F10: Busy | G10: 40 | H10: =COUNTIF(tblTasks[Assigned User],[@[User ID]]) | I10: =COUNTIFS(tblTasks[Assigned User],[@[User ID]],tblTasks[Manual Status],"<>Completed",tblTasks[Manual Status],"<>Cancelled") | J10: =COUNTIFS(tblTasks[Assigned User],[@[User ID]],tblTasks[Auto Health],"Overdue") | K10: =SUMIF(tblTimesheets[User ID],[@[User ID]],tblTimesheets[Hours]) | L10: =IFERROR([@[Logged Hours]]/([@[Capacity Hours/Week]]*4),0)
A11: USR-006 | B11: Fatima Khan | C11: fatima@example.com | D11: Support | E11: Business Analyst | F11: Available | G11: 40 | H11: =COUNTIF(tblTasks[Assigned User],[@[User ID]]) | I11: =COUNTIFS(tblTasks[Assigned User],[@[User ID]],tblTasks[Manual Status],"<>Completed",tblTasks[Manual Status],"<>Cancelled") | J11: =COUNTIFS(tblTasks[Assigned User],[@[User ID]],tblTasks[Auto Health],"Overdue") | K11: =SUMIF(tblTimesheets[User ID],[@[User ID]],tblTimesheets[Hours]) | L11: =IFERROR([@[Logged Hours]]/([@[Capacity Hours/Week]]*4),0)

Sheet Teams
A1: Teams
A2: Zoho-style teams/squads
A3: Home | B3: Dashboard | C3: Workspace | D3: Projects | E3: Tasks | F3: Issues | G3: Timesheets | H3: Reports | I3: Master
A5: Team ID | B5: Team Name | C5: Lead User | D5: Department | E5: Notes
A6: TEAM-001 | B6: Platform Squad | C6: USR-001 | D6: Engineering | E6: Core app delivery
A7: TEAM-002 | B7: Quality Guild | C7: USR-004 | D7: QA | E7: Testing and release assurance
A8: TEAM-003 | B8: Operations Cell | C8: USR-005 | D8: Operations | E8: Deployment and support

Sheet Clients
A1: Clients
A2: Client and department master
A3: Home | B3: Dashboard | C3: Workspace | D3: Projects | E3: Tasks | F3: Issues | G3: Timesheets | H3: Reports | I3: Master
A5: Client ID | B5: Client / Department | C5: Type | D5: Contact Name | E5: Contact Email
A6: CL-001 | B6: Finance Department | C6: Internal | D6: Anjali Verma | E6: anjali@example.com
A7: CL-002 | B7: Sales Department | C7: Internal | D7: Raj Mehta | E7: raj@example.com
A8: CL-003 | B8: Operations Group | C8: Internal | D8: Kiran Rao | E8: kiran@example.com
A9: CL-004 | B9: External Client A | C9: External | D9: Divya Shah | E9: divya@example.com

Sheet Reports
A1: Reports
A2: Ready-to-use PMO reports
A3: Home | B3: Dashboard | C3: Workspace | D3: Projects | E3: Tasks | F3: Issues | G3: Timesheets | H3: Reports | I3: Master
A5: Overdue Tasks
A6: Task ID | B6: Project ID | C6: Task | D6: Owner | E6: Due Date | F6: Days Late | G6: Priority
A7: =IFERROR(INDEX(FILTER(tblTasks[Task ID],tblTasks[Auto Health]="Overdue"),1),"") | B7: =IFERROR(INDEX(FILTER(tblTasks[Project ID],tblTasks[Auto Health]="Overdue"),1),"") | C7: =IFERROR(INDEX(FILTER(tblTasks[Task Name],tblTasks[Auto Health]="Overdue"),1),"") | D7: =IFERROR(INDEX(FILTER(tblTasks[Assigned User],tblTasks[Auto Health]="Overdue"),1),"") | E7: =IFERROR(INDEX(FILTER(tblTasks[Due Date],tblTasks[Auto Health]="Overdue"),1),"") | F7: =IFERROR(INDEX(FILTER(tblTasks[Days Late],tblTasks[Auto Health]="Overdue"),1),"") | G7: =IFERROR(INDEX(FILTER(tblTasks[Priority],tblTasks[Auto Health]="Overdue"),1),"")
A8: =IFERROR(INDEX(FILTER(tblTasks[Task ID],tblTasks[Auto Health]="Overdue"),2),"") | B8: =IFERROR(INDEX(FILTER(tblTasks[Project ID],tblTasks[Auto Health]="Overdue"),2),"") | C8: =IFERROR(INDEX(FILTER(tblTasks[Task Name],tblTasks[Auto Health]="Overdue"),2),"") | D8: =IFERROR(INDEX(FILTER(tblTasks[Assigned User],tblTasks[Auto Health]="Overdue"),2),"") | E8: =IFERROR(INDEX(FILTER(tblTasks[Due Date],tblTasks[Auto Health]="Overdue"),2),"") | F8: =IFERROR(INDEX(FILTER(tblTasks[Days Late],tblTasks[Auto Health]="Overdue"),2),"") | G8: =IFERROR(INDEX(FILTER(tblTasks[Priority],tblTasks[Auto Health]="Overdue"),2),"")
A9: =IFERROR(INDEX(FILTER(tblTasks[Task ID],tblTasks[Auto Health]="Overdue"),3),"") | B9: =IFERROR(INDEX(FILTER(tblTasks[Project ID],tblTasks[Auto Health]="Overdue"),3),"") | C9: =IFERROR(INDEX(FILTER(tblTasks[Task Name],tblTasks[Auto Health]="Overdue"),3),"") | D9: =IFERROR(INDEX(FILTER(tblTasks[Assigned User],tblTasks[Auto Health]="Overdue"),3),"") | E9: =IFERROR(INDEX(FILTER(tblTasks[Due Date],tblTasks[Auto Health]="Overdue"),3),"") | F9: =IFERROR(INDEX(FILTER(tblTasks[Days Late],tblTasks[Auto Health]="Overdue"),3),"") | G9: =IFERROR(INDEX(FILTER(tblTasks[Priority],tblTasks[Auto Health]="Overdue"),3),"")
A10: =IFERROR(INDEX(FILTER(tblTasks[Task ID],tblTasks[Auto Health]="Overdue"),4),"") | B10: =IFERROR(INDEX(FILTER(tblTasks[Project ID],tblTasks[Auto Health]="Overdue"),4),"") | C10: =IFERROR(INDEX(FILTER(tblTasks[Task Name],tblTasks[Auto Health]="Overdue"),4),"") | D10: =IFERROR(INDEX(FILTER(tblTasks[Assigned User],tblTasks[Auto Health]="Overdue"),4),"") | E10: =IFERROR(INDEX(FILTER(tblTasks[Due Date],tblTasks[Auto Health]="Overdue"),4),"") | F10: =IFERROR(INDEX(FILTER(tblTasks[Days Late],tblTasks[Auto Health]="Overdue"),4),"") | G10: =IFERROR(INDEX(FILTER(tblTasks[Priority],tblTasks[Auto Health]="Overdue"),4),"")
A11: =IFERROR(INDEX(FILTER(tblTasks[Task ID],tblTasks[Auto Health]="Overdue"),5),"") | B11: =IFERROR(INDEX(FILTER(tblTasks[Project ID],tblTasks[Auto Health]="Overdue"),5),"") | C11: =IFERROR(INDEX(FILTER(tblTasks[Task Name],tblTasks[Auto Health]="Overdue"),5),"") | D11: =IFERROR(INDEX(FILTER(tblTasks[Assigned User],tblTasks[Auto Health]="Overdue"),5),"") | E11: =IFERROR(INDEX(FILTER(tblTasks[Due Date],tblTasks[Auto Health]="Overdue"),5),"") | F11: =IFERROR(INDEX(FILTER(tblTasks[Days Late],tblTasks[Auto Health]="Overdue"),5),"") | G11: =IFERROR(INDEX(FILTER(tblTasks[Priority],tblTasks[Auto Health]="Overdue"),5),"")
A12: =IFERROR(INDEX(FILTER(tblTasks[Task ID],tblTasks[Auto Health]="Overdue"),6),"") | B12: =IFERROR(INDEX(FILTER(tblTasks[Project ID],tblTasks[Auto Health]="Overdue"),6),"") | C12: =IFERROR(INDEX(FILTER(tblTasks[Task Name],tblTasks[Auto Health]="Overdue"),6),"") | D12: =IFERROR(INDEX(FILTER(tblTasks[Assigned User],tblTasks[Auto Health]="Overdue"),6),"") | E12: =IFERROR(INDEX(FILTER(tblTasks[Due Date],tblTasks[Auto Health]="Overdue"),6),"") | F12: =IFERROR(INDEX(FILTER(tblTasks[Days Late],tblTasks[Auto Health]="Overdue"),6),"") | G12: =IFERROR(INDEX(FILTER(tblTasks[Priority],tblTasks[Auto Health]="Overdue"),6),"")
A13: =IFERROR(INDEX(FILTER(tblTasks[Task ID],tblTasks[Auto Health]="Overdue"),7),"") | B13: =IFERROR(INDEX(FILTER(tblTasks[Project ID],tblTasks[Auto Health]="Overdue"),7),"") | C13: =IFERROR(INDEX(FILTER(tblTasks[Task Name],tblTasks[Auto Health]="Overdue"),7),"") | D13: =IFERROR(INDEX(FILTER(tblTasks[Assigned User],tblTasks[Auto Health]="Overdue"),7),"") | E13: =IFERROR(INDEX(FILTER(tblTasks[Due Date],tblTasks[Auto Health]="Overdue"),7),"") | F13: =IFERROR(INDEX(FILTER(tblTasks[Days Late],tblTasks[Auto Health]="Overdue"),7),"") | G13: =IFERROR(INDEX(FILTER(tblTasks[Priority],tblTasks[Auto Health]="Overdue"),7),"")
A14: =IFERROR(INDEX(FILTER(tblTasks[Task ID],tblTasks[Auto Health]="Overdue"),8),"") | B14: =IFERROR(INDEX(FILTER(tblTasks[Project ID],tblTasks[Auto Health]="Overdue"),8),"") | C14: =IFERROR(INDEX(FILTER(tblTasks[Task Name],tblTasks[Auto Health]="Overdue"),8),"") | D14: =IFERROR(INDEX(FILTER(tblTasks[Assigned User],tblTasks[Auto Health]="Overdue"),8),"") | E14: =IFERROR(INDEX(FILTER(tblTasks[Due Date],tblTasks[Auto Health]="Overdue"),8),"") | F14: =IFERROR(INDEX(FILTER(tblTasks[Days Late],tblTasks[Auto Health]="Overdue"),8),"") | G14: =IFERROR(INDEX(FILTER(tblTasks[Priority],tblTasks[Auto Health]="Overdue"),8),"")
A15: =IFERROR(INDEX(FILTER(tblTasks[Task ID],tblTasks[Auto Health]="Overdue"),9),"") | B15: =IFERROR(INDEX(FILTER(tblTasks[Project ID],tblTasks[Auto Health]="Overdue"),9),"") | C15: =IFERROR(INDEX(FILTER(tblTasks[Task Name],tblTasks[Auto Health]="Overdue"),9),"") | D15: =IFERROR(INDEX(FILTER(tblTasks[Assigned User],tblTasks[Auto Health]="Overdue"),9),"") | E15: =IFERROR(INDEX(FILTER(tblTasks[Due Date],tblTasks[Auto Health]="Overdue"),9),"") | F15: =IFERROR(INDEX(FILTER(tblTasks[Days Late],tblTasks[Auto Health]="Overdue"),9),"") | G15: =IFERROR(INDEX(FILTER(tblTasks[Priority],tblTasks[Auto Health]="Overdue"),9),"")
A16: =IFERROR(INDEX(FILTER(tblTasks[Task ID],tblTasks[Auto Health]="Overdue"),10),"") | B16: =IFERROR(INDEX(FILTER(tblTasks[Project ID],tblTasks[Auto Health]="Overdue"),10),"") | C16: =IFERROR(INDEX(FILTER(tblTasks[Task Name],tblTasks[Auto Health]="Overdue"),10),"") | D16: =IFERROR(INDEX(FILTER(tblTasks[Assigned User],tblTasks[Auto Health]="Overdue"),10),"") | E16: =IFERROR(INDEX(FILTER(tblTasks[Due Date],tblTasks[Auto Health]="Overdue"),10),"") | F16: =IFERROR(INDEX(FILTER(tblTasks[Days Late],tblTasks[Auto Health]="Overdue"),10),"") | G16: =IFERROR(INDEX(FILTER(tblTasks[Priority],tblTasks[Auto Health]="Overdue"),10),"")
A17: =IFERROR(INDEX(FILTER(tblTasks[Task ID],tblTasks[Auto Health]="Overdue"),11),"") | B17: =IFERROR(INDEX(FILTER(tblTasks[Project ID],tblTasks[Auto Health]="Overdue"),11),"") | C17: =IFERROR(INDEX(FILTER(tblTasks[Task Name],tblTasks[Auto Health]="Overdue"),11),"") | D17: =IFERROR(INDEX(FILTER(tblTasks[Assigned User],tblTasks[Auto Health]="Overdue"),11),"") | E17: =IFERROR(INDEX(FILTER(tblTasks[Due Date],tblTasks[Auto Health]="Overdue"),11),"") | F17: =IFERROR(INDEX(FILTER(tblTasks[Days Late],tblTasks[Auto Health]="Overdue"),11),"") | G17: =IFERROR(INDEX(FILTER(tblTasks[Priority],tblTasks[Auto Health]="Overdue"),11),"")
A18: =IFERROR(INDEX(FILTER(tblTasks[Task ID],tblTasks[Auto Health]="Overdue"),12),"") | B18: =IFERROR(INDEX(FILTER(tblTasks[Project ID],tblTasks[Auto Health]="Overdue"),12),"") | C18: =IFERROR(INDEX(FILTER(tblTasks[Task Name],tblTasks[Auto Health]="Overdue"),12),"") | D18: =IFERROR(INDEX(FILTER(tblTasks[Assigned User],tblTasks[Auto Health]="Overdue"),12),"") | E18: =IFERROR(INDEX(FILTER(tblTasks[Due Date],tblTasks[Auto Health]="Overdue"),12),"") | F18: =IFERROR(INDEX(FILTER(tblTasks[Days Late],tblTasks[Auto Health]="Overdue"),12),"") | G18: =IFERROR(INDEX(FILTER(tblTasks[Priority],tblTasks[Auto Health]="Overdue"),12),"")
A19: =IFERROR(INDEX(FILTER(tblTasks[Task ID],tblTasks[Auto Health]="Overdue"),13),"") | B19: =IFERROR(INDEX(FILTER(tblTasks[Project ID],tblTasks[Auto Health]="Overdue"),13),"") | C19: =IFERROR(INDEX(FILTER(tblTasks[Task Name],tblTasks[Auto Health]="Overdue"),13),"") | D19: =IFERROR(INDEX(FILTER(tblTasks[Assigned User],tblTasks[Auto Health]="Overdue"),13),"") | E19: =IFERROR(INDEX(FILTER(tblTasks[Due Date],tblTasks[Auto Health]="Overdue"),13),"") | F19: =IFERROR(INDEX(FILTER(tblTasks[Days Late],tblTasks[Auto Health]="Overdue"),13),"") | G19: =IFERROR(INDEX(FILTER(tblTasks[Priority],tblTasks[Auto Health]="Overdue"),13),"")
A20: =IFERROR(INDEX(FILTER(tblTasks[Task ID],tblTasks[Auto Health]="Overdue"),14),"") | B20: =IFERROR(INDEX(FILTER(tblTasks[Project ID],tblTasks[Auto Health]="Overdue"),14),"") | C20: =IFERROR(INDEX(FILTER(tblTasks[Task Name],tblTasks[Auto Health]="Overdue"),14),"") | D20: =IFERROR(INDEX(FILTER(tblTasks[Assigned User],tblTasks[Auto Health]="Overdue"),14),"") | E20: =IFERROR(INDEX(FILTER(tblTasks[Due Date],tblTasks[Auto Health]="Overdue"),14),"") | F20: =IFERROR(INDEX(FILTER(tblTasks[Days Late],tblTasks[Auto Health]="Overdue"),14),"") | G20: =IFERROR(INDEX(FILTER(tblTasks[Priority],tblTasks[Auto Health]="Overdue"),14),"")
A21: =IFERROR(INDEX(FILTER(tblTasks[Task ID],tblTasks[Auto Health]="Overdue"),15),"") | B21: =IFERROR(INDEX(FILTER(tblTasks[Project ID],tblTasks[Auto Health]="Overdue"),15),"") | C21: =IFERROR(INDEX(FILTER(tblTasks[Task Name],tblTasks[Auto Health]="Overdue"),15),"") | D21: =IFERROR(INDEX(FILTER(tblTasks[Assigned User],tblTasks[Auto Health]="Overdue"),15),"") | E21: =IFERROR(INDEX(FILTER(tblTasks[Due Date],tblTasks[Auto Health]="Overdue"),15),"") | F21: =IFERROR(INDEX(FILTER(tblTasks[Days Late],tblTasks[Auto Health]="Overdue"),15),"") | G21: =IFERROR(INDEX(FILTER(tblTasks[Priority],tblTasks[Auto Health]="Overdue"),15),"")
A25: User Workload
A26: User | B26: Department | C26: Active Tasks | D26: Overdue Tasks | E26: Logged Hours | F26: Utilization
A27: =IFERROR(INDEX(tblUsers[Full Name],1),"") | B27: =IFERROR(INDEX(tblUsers[Department],1),"") | C27: =IFERROR(INDEX(tblUsers[Active Tasks],1),"") | D27: =IFERROR(INDEX(tblUsers[Overdue Tasks],1),"") | E27: =IFERROR(INDEX(tblUsers[Logged Hours],1),"") | F27: =IFERROR(INDEX(tblUsers[Utilization %],1),"")
A28: =IFERROR(INDEX(tblUsers[Full Name],2),"") | B28: =IFERROR(INDEX(tblUsers[Department],2),"") | C28: =IFERROR(INDEX(tblUsers[Active Tasks],2),"") | D28: =IFERROR(INDEX(tblUsers[Overdue Tasks],2),"") | E28: =IFERROR(INDEX(tblUsers[Logged Hours],2),"") | F28: =IFERROR(INDEX(tblUsers[Utilization %],2),"")
A29: =IFERROR(INDEX(tblUsers[Full Name],3),"") | B29: =IFERROR(INDEX(tblUsers[Department],3),"") | C29: =IFERROR(INDEX(tblUsers[Active Tasks],3),"") | D29: =IFERROR(INDEX(tblUsers[Overdue Tasks],3),"") | E29: =IFERROR(INDEX(tblUsers[Logged Hours],3),"") | F29: =IFERROR(INDEX(tblUsers[Utilization %],3),"")
A30: =IFERROR(INDEX(tblUsers[Full Name],4),"") | B30: =IFERROR(INDEX(tblUsers[Department],4),"") | C30: =IFERROR(INDEX(tblUsers[Active Tasks],4),"") | D30: =IFERROR(INDEX(tblUsers[Overdue Tasks],4),"") | E30: =IFERROR(INDEX(tblUsers[Logged Hours],4),"") | F30: =IFERROR(INDEX(tblUsers[Utilization %],4),"")
A31: =IFERROR(INDEX(tblUsers[Full Name],5),"") | B31: =IFERROR(INDEX(tblUsers[Department],5),"") | C31: =IFERROR(INDEX(tblUsers[Active Tasks],5),"") | D31: =IFERROR(INDEX(tblUsers[Overdue Tasks],5),"") | E31: =IFERROR(INDEX(tblUsers[Logged Hours],5),"") | F31: =IFERROR(INDEX(tblUsers[Utilization %],5),"")
A32: =IFERROR(INDEX(tblUsers[Full Name],6),"") | B32: =IFERROR(INDEX(tblUsers[Department],6),"") | C32: =IFERROR(INDEX(tblUsers[Active Tasks],6),"") | D32: =IFERROR(INDEX(tblUsers[Overdue Tasks],6),"") | E32: =IFERROR(INDEX(tblUsers[Logged Hours],6),"") | F32: =IFERROR(INDEX(tblUsers[Utilization %],6),"")
A33: =IFERROR(INDEX(tblUsers[Full Name],7),"") | B33: =IFERROR(INDEX(tblUsers[Department],7),"") | C33: =IFERROR(INDEX(tblUsers[Active Tasks],7),"") | D33: =IFERROR(INDEX(tblUsers[Overdue Tasks],7),"") | E33: =IFERROR(INDEX(tblUsers[Logged Hours],7),"") | F33: =IFERROR(INDEX(tblUsers[Utilization %],7),"")
A34: =IFERROR(INDEX(tblUsers[Full Name],8),"") | B34: =IFERROR(INDEX(tblUsers[Department],8),"") | C34: =IFERROR(INDEX(tblUsers[Active Tasks],8),"") | D34: =IFERROR(INDEX(tblUsers[Overdue Tasks],8),"") | E34: =IFERROR(INDEX(tblUsers[Logged Hours],8),"") | F34: =IFERROR(INDEX(tblUsers[Utilization %],8),"")
A35: =IFERROR(INDEX(tblUsers[Full Name],9),"") | B35: =IFERROR(INDEX(tblUsers[Department],9),"") | C35: =IFERROR(INDEX(tblUsers[Active Tasks],9),"") | D35: =IFERROR(INDEX(tblUsers[Overdue Tasks],9),"") | E35: =IFERROR(INDEX(tblUsers[Logged Hours],9),"") | F35: =IFERROR(INDEX(tblUsers[Utilization %],9),"")
A36: =IFERROR(INDEX(tblUsers[Full Name],10),"") | B36: =IFERROR(INDEX(tblUsers[Department],10),"") | C36: =IFERROR(INDEX(tblUsers[Active Tasks],10),"") | D36: =IFERROR(INDEX(tblUsers[Overdue Tasks],10),"") | E36: =IFERROR(INDEX(tblUsers[Logged Hours],10),"") | F36: =IFERROR(INDEX(tblUsers[Utilization %],10),"")

Sheet Master_Management
A1: Master Management
A2: Central dropdown lists for every module
A3: Home | B3: Dashboard | C3: Workspace | D3: Projects | E3: Tasks | F3: Issues | G3: Timesheets | H3: Reports | I3: Master
A5: Project_Status | B5: Task_Status | C5: Priority | D5: Health | E5: Issue_Status | F5: Issue_Type | G5: Risk_Status | H5: Billable | I5: Department | J5: Role | K5: Activity_Type | L5: Document_Type
A6: Not Started | B6: Not Started | C6: Critical | D6: On Track | E6: Open | F6: Bug | G6: Open | H6: Billable | I6: PMO | J6: Project Manager | K6: Comment | L6: BRD
A7: Planning | B7: In Progress | C7: High | D7: At Risk | E7: In Progress | F7: Change Request | G7: Mitigating | H7: Non-Billable | I7: Engineering | J7: Business Analyst | K7: Status Change | L7: Design
A8: In Progress | B8: Blocked | C8: Medium | D8: Overdue | E8: Waiting | F8: Support | G8: Accepted | I8: Design | J8: Developer | K8: File Uploaded | L8: Test Evidence
A9: On Hold | B9: On Hold | C9: Low | D9: Blocked | E9: Resolved | F9: Dependency | G9: Closed | I9: QA | J9: Designer | K9: Meeting | L9: SOP
A10: Completed | B10: In Review | D10: Completed | E10: Closed | F10: Decision | G10: Escalated | I10: Operations | J10: QA Engineer | K10: Approval | L10: Minutes
A11: Cancelled | B11: Completed | D11: Not Started | E11: Rejected | F11: Blocker | I11: Finance | J11: DevOps | K11: Escalation | L11: Contract
A12: Archived | B12: Cancelled | I12: Sales | J12: Stakeholder | K12: Decision | L12: Report
I13: Support | J13: Approver | L13: Other
I14: HR | J14: Finance Owner
I15: Legal

Sheet Settings
A1: Settings
A2: Workbook configuration and report controls
A3: Home | B3: Dashboard | C3: Workspace | D3: Projects | E3: Tasks | F3: Issues | G3: Timesheets | H3: Reports | I3: Master
A5: Company Name | B5: Your Company
A6: Default Currency | B6: INR
A7: Reporting Date | B7: =TODAY()
A8: Portfolio Owner | B8: PMO
A9: Default Working Week | B9: Mon-Fri
A10: Version | B10: 2.0 Zoho-style workspace

Sheet How_To_Use
A1: How To Use
A2: Operating notes for the Zoho-style workbook
A3: Home | B3: Dashboard | C3: Workspace | D3: Projects | E3: Tasks | F3: Issues | G3: Timesheets | H3: Reports | I3: Master
A5: 1 | B5: Start from Home or Portfolio Dashboard for overall navigation.
A6: 2 | B6: Use Projects as the portfolio master; every task, issue, risk, milestone, document and timesheet row links back to Project ID.
A7: 3 | B7: Use Project Workspace to pick one Project ID and view its task snapshot and activity stream.
A8: 4 | B8: Use Kanban View for a simple status board.
A9: 5 | B9: Use Timesheets for effort tracking and Reports for overdue/workload outputs.
A10: 6 | B10: Add dropdown values in Master Management before expanding company-specific fields.

Sheet Executive_Dashboard
A1: Executive Dashboard
A2: Desktop PMO dashboard for portfolio leadership
A3: Home | B3: Exec | C3: Compact | D3: Project | E3: Tasks | F3: Kanban | G3: Gantt | H3: Reports | I3: Master
A5: =COUNTA(tblProjects[Project ID]) | D5: =COUNTIFS(tblProjects[Manual Status],"In Progress") | G5: =COUNTIFS(tblProjects[Auto Health],"At Risk")+COUNTIFS(tblProjects[Auto Health],"Overdue") | J5: =COUNTIFS(tblProjects[Manual Status],"Completed")
A8: Total Projects | D8: Active Projects | G8: At Risk / Overdue | J8: Completed Projects
A10: =COUNTIFS(tblIssues[Status],"<>Closed",tblIssues[Status],"<>Resolved") | D10: =COUNTIFS(tblRisks[Status],"<>Closed") | G10: =SUM(tblTimesheets[Hours]) | J10: =SUM(tblProjects[Actual Cost])-SUM(tblProjects[Budget])
A13: Open Issues | D13: Open Risks | G13: Logged Hours | J13: Budget Variance
A16: Project Health | D16: Task Status | G16: Priority Mix | J16: User Workload
A17: Health | B17: Count | D17: Status | E17: Count | G17: Priority | H17: Count | J17: User | K17: Active Tasks
A18: On Track | B18: =COUNTIF(tblProjects[Auto Health],A18) | D18: On Track | E18: =COUNTIF(tblTasks[Auto Health],D18) | G18: Critical | H18: =COUNTIF(tblTasks[Priority],G18) | J18: =Users!B6 | K18: =Users!I6
A19: At Risk | B19: =COUNTIF(tblProjects[Auto Health],A19) | D19: At Risk | E19: =COUNTIF(tblTasks[Auto Health],D19) | G19: High | H19: =COUNTIF(tblTasks[Priority],G19) | J19: =Users!B7 | K19: =Users!I7
A20: Overdue | B20: =COUNTIF(tblProjects[Auto Health],A20) | D20: Overdue | E20: =COUNTIF(tblTasks[Auto Health],D20) | G20: Medium | H20: =COUNTIF(tblTasks[Priority],G20) | J20: =Users!B8 | K20: =Users!I8
A21: Blocked | B21: =COUNTIF(tblProjects[Auto Health],A21) | D21: Blocked | E21: =COUNTIF(tblTasks[Auto Health],D21) | G21: Low | H21: =COUNTIF(tblTasks[Priority],G21) | J21: =Users!B9 | K21: =Users!I9
A22: Completed | B22: =COUNTIF(tblProjects[Auto Health],A22) | D22: Completed | E22: =COUNTIF(tblTasks[Auto Health],D22) | J22: =Users!B10 | K22: =Users!I10
A23: Not Started | B23: =COUNTIF(tblProjects[Auto Health],A23) | D23: Not Started | E23: =COUNTIF(tblTasks[Auto Health],D23) | J23: =Users!B11 | K23: =Users!I11
A26: Portfolio List
A27: Project ID | B27: Project | C27: Status | D27: Priority | E27: Progress | F27: Health | G27: Open Issues | H27: Open Risks | I27: Hours
A28: =IFERROR(INDEX(tblProjects[Project ID],1),"") | B28: =IFERROR(INDEX(tblProjects[Project Name],1),"") | C28: =IFERROR(INDEX(tblProjects[Manual Status],1),"") | D28: =IFERROR(INDEX(tblProjects[Priority],1),"") | E28: =IFERROR(INDEX(tblProjects[Progress %],1),"") | F28: =IFERROR(INDEX(tblProjects[Auto Health],1),"") | G28: =IFERROR(INDEX(tblProjects[Open Issues],1),"") | H28: =IFERROR(INDEX(tblProjects[Open Risks],1),"") | I28: =IFERROR(INDEX(tblProjects[Logged Hours],1),"")
A29: =IFERROR(INDEX(tblProjects[Project ID],2),"") | B29: =IFERROR(INDEX(tblProjects[Project Name],2),"") | C29: =IFERROR(INDEX(tblProjects[Manual Status],2),"") | D29: =IFERROR(INDEX(tblProjects[Priority],2),"") | E29: =IFERROR(INDEX(tblProjects[Progress %],2),"") | F29: =IFERROR(INDEX(tblProjects[Auto Health],2),"") | G29: =IFERROR(INDEX(tblProjects[Open Issues],2),"") | H29: =IFERROR(INDEX(tblProjects[Open Risks],2),"") | I29: =IFERROR(INDEX(tblProjects[Logged Hours],2),"")
A30: =IFERROR(INDEX(tblProjects[Project ID],3),"") | B30: =IFERROR(INDEX(tblProjects[Project Name],3),"") | C30: =IFERROR(INDEX(tblProjects[Manual Status],3),"") | D30: =IFERROR(INDEX(tblProjects[Priority],3),"") | E30: =IFERROR(INDEX(tblProjects[Progress %],3),"") | F30: =IFERROR(INDEX(tblProjects[Auto Health],3),"") | G30: =IFERROR(INDEX(tblProjects[Open Issues],3),"") | H30: =IFERROR(INDEX(tblProjects[Open Risks],3),"") | I30: =IFERROR(INDEX(tblProjects[Logged Hours],3),"")
A31: =IFERROR(INDEX(tblProjects[Project ID],4),"") | B31: =IFERROR(INDEX(tblProjects[Project Name],4),"") | C31: =IFERROR(INDEX(tblProjects[Manual Status],4),"") | D31: =IFERROR(INDEX(tblProjects[Priority],4),"") | E31: =IFERROR(INDEX(tblProjects[Progress %],4),"") | F31: =IFERROR(INDEX(tblProjects[Auto Health],4),"") | G31: =IFERROR(INDEX(tblProjects[Open Issues],4),"") | H31: =IFERROR(INDEX(tblProjects[Open Risks],4),"") | I31: =IFERROR(INDEX(tblProjects[Logged Hours],4),"")
A32: =IFERROR(INDEX(tblProjects[Project ID],5),"") | B32: =IFERROR(INDEX(tblProjects[Project Name],5),"") | C32: =IFERROR(INDEX(tblProjects[Manual Status],5),"") | D32: =IFERROR(INDEX(tblProjects[Priority],5),"") | E32: =IFERROR(INDEX(tblProjects[Progress %],5),"") | F32: =IFERROR(INDEX(tblProjects[Auto Health],5),"") | G32: =IFERROR(INDEX(tblProjects[Open Issues],5),"") | H32: =IFERROR(INDEX(tblProjects[Open Risks],5),"") | I32: =IFERROR(INDEX(tblProjects[Logged Hours],5),"")
A33: =IFERROR(INDEX(tblProjects[Project ID],6),"") | B33: =IFERROR(INDEX(tblProjects[Project Name],6),"") | C33: =IFERROR(INDEX(tblProjects[Manual Status],6),"") | D33: =IFERROR(INDEX(tblProjects[Priority],6),"") | E33: =IFERROR(INDEX(tblProjects[Progress %],6),"") | F33: =IFERROR(INDEX(tblProjects[Auto Health],6),"") | G33: =IFERROR(INDEX(tblProjects[Open Issues],6),"") | H33: =IFERROR(INDEX(tblProjects[Open Risks],6),"") | I33: =IFERROR(INDEX(tblProjects[Logged Hours],6),"")
A34: =IFERROR(INDEX(tblProjects[Project ID],7),"") | B34: =IFERROR(INDEX(tblProjects[Project Name],7),"") | C34: =IFERROR(INDEX(tblProjects[Manual Status],7),"") | D34: =IFERROR(INDEX(tblProjects[Priority],7),"") | E34: =IFERROR(INDEX(tblProjects[Progress %],7),"") | F34: =IFERROR(INDEX(tblProjects[Auto Health],7),"") | G34: =IFERROR(INDEX(tblProjects[Open Issues],7),"") | H34: =IFERROR(INDEX(tblProjects[Open Risks],7),"") | I34: =IFERROR(INDEX(tblProjects[Logged Hours],7),"")
A35: =IFERROR(INDEX(tblProjects[Project ID],8),"") | B35: =IFERROR(INDEX(tblProjects[Project Name],8),"") | C35: =IFERROR(INDEX(tblProjects[Manual Status],8),"") | D35: =IFERROR(INDEX(tblProjects[Priority],8),"") | E35: =IFERROR(INDEX(tblProjects[Progress %],8),"") | F35: =IFERROR(INDEX(tblProjects[Auto Health],8),"") | G35: =IFERROR(INDEX(tblProjects[Open Issues],8),"") | H35: =IFERROR(INDEX(tblProjects[Open Risks],8),"") | I35: =IFERROR(INDEX(tblProjects[Logged Hours],8),"")
A36: =IFERROR(INDEX(tblProjects[Project ID],9),"") | B36: =IFERROR(INDEX(tblProjects[Project Name],9),"") | C36: =IFERROR(INDEX(tblProjects[Manual Status],9),"") | D36: =IFERROR(INDEX(tblProjects[Priority],9),"") | E36: =IFERROR(INDEX(tblProjects[Progress %],9),"") | F36: =IFERROR(INDEX(tblProjects[Auto Health],9),"") | G36: =IFERROR(INDEX(tblProjects[Open Issues],9),"") | H36: =IFERROR(INDEX(tblProjects[Open Risks],9),"") | I36: =IFERROR(INDEX(tblProjects[Logged Hours],9),"")
A37: =IFERROR(INDEX(tblProjects[Project ID],10),"") | B37: =IFERROR(INDEX(tblProjects[Project Name],10),"") | C37: =IFERROR(INDEX(tblProjects[Manual Status],10),"") | D37: =IFERROR(INDEX(tblProjects[Priority],10),"") | E37: =IFERROR(INDEX(tblProjects[Progress %],10),"") | F37: =IFERROR(INDEX(tblProjects[Auto Health],10),"") | G37: =IFERROR(INDEX(tblProjects[Open Issues],10),"") | H37: =IFERROR(INDEX(tblProjects[Open Risks],10),"") | I37: =IFERROR(INDEX(tblProjects[Logged Hours],10),"")

Sheet Project_Command_Center
A1: Project Command Center
A2: Single-project command center with project selector
A3: Home | B3: Exec | C3: Compact | D3: Project | E3: Tasks | F3: Kanban | G3: Gantt | H3: Reports | I3: Master
A5: Select Project ID | B5: PRJ-001
A7: Project Name | B7: =XLOOKUP($B$5,tblProjects[Project ID],tblProjects[Project Name],"") | D7: Manager | E7: =XLOOKUP($B$5,tblProjects[Project ID],tblProjects[Project Manager],"") | G7: Status | H7: =XLOOKUP($B$5,tblProjects[Project ID],tblProjects[Manual Status],"") | J7: Health | K7: =XLOOKUP($B$5,tblProjects[Project ID],tblProjects[Auto Health],"")
A9: Progress | B9: =XLOOKUP($B$5,tblProjects[Project ID],tblProjects[Progress %],"") | D9: Open Issues | E9: =XLOOKUP($B$5,tblProjects[Project ID],tblProjects[Open Issues],"") | G9: Open Risks | H9: =XLOOKUP($B$5,tblProjects[Project ID],tblProjects[Open Risks],"") | J9: Logged Hours | K9: =XLOOKUP($B$5,tblProjects[Project ID],tblProjects[Logged Hours],"")
A12: Project Task Snapshot
A13: Task ID | B13: Task Name | C13: Owner | D13: Status | E13: Priority | F13: Progress | G13: Health | H13: Due Date
A14: =IFERROR(INDEX(FILTER(tblTasks[Task ID],tblTasks[Project ID]=$B$5),1),"") | B14: =IFERROR(INDEX(FILTER(tblTasks[Task Name],tblTasks[Project ID]=$B$5),1),"") | C14: =IFERROR(INDEX(FILTER(tblTasks[Assigned User],tblTasks[Project ID]=$B$5),1),"") | D14: =IFERROR(INDEX(FILTER(tblTasks[Manual Status],tblTasks[Project ID]=$B$5),1),"") | E14: =IFERROR(INDEX(FILTER(tblTasks[Priority],tblTasks[Project ID]=$B$5),1),"") | F14: =IFERROR(INDEX(FILTER(tblTasks[Progress %],tblTasks[Project ID]=$B$5),1),"") | G14: =IFERROR(INDEX(FILTER(tblTasks[Auto Health],tblTasks[Project ID]=$B$5),1),"") | H14: =IFERROR(INDEX(FILTER(tblTasks[Due Date],tblTasks[Project ID]=$B$5),1),"")
A15: =IFERROR(INDEX(FILTER(tblTasks[Task ID],tblTasks[Project ID]=$B$5),2),"") | B15: =IFERROR(INDEX(FILTER(tblTasks[Task Name],tblTasks[Project ID]=$B$5),2),"") | C15: =IFERROR(INDEX(FILTER(tblTasks[Assigned User],tblTasks[Project ID]=$B$5),2),"") | D15: =IFERROR(INDEX(FILTER(tblTasks[Manual Status],tblTasks[Project ID]=$B$5),2),"") | E15: =IFERROR(INDEX(FILTER(tblTasks[Priority],tblTasks[Project ID]=$B$5),2),"") | F15: =IFERROR(INDEX(FILTER(tblTasks[Progress %],tblTasks[Project ID]=$B$5),2),"") | G15: =IFERROR(INDEX(FILTER(tblTasks[Auto Health],tblTasks[Project ID]=$B$5),2),"") | H15: =IFERROR(INDEX(FILTER(tblTasks[Due Date],tblTasks[Project ID]=$B$5),2),"")
A16: =IFERROR(INDEX(FILTER(tblTasks[Task ID],tblTasks[Project ID]=$B$5),3),"") | B16: =IFERROR(INDEX(FILTER(tblTasks[Task Name],tblTasks[Project ID]=$B$5),3),"") | C16: =IFERROR(INDEX(FILTER(tblTasks[Assigned User],tblTasks[Project ID]=$B$5),3),"") | D16: =IFERROR(INDEX(FILTER(tblTasks[Manual Status],tblTasks[Project ID]=$B$5),3),"") | E16: =IFERROR(INDEX(FILTER(tblTasks[Priority],tblTasks[Project ID]=$B$5),3),"") | F16: =IFERROR(INDEX(FILTER(tblTasks[Progress %],tblTasks[Project ID]=$B$5),3),"") | G16: =IFERROR(INDEX(FILTER(tblTasks[Auto Health],tblTasks[Project ID]=$B$5),3),"") | H16: =IFERROR(INDEX(FILTER(tblTasks[Due Date],tblTasks[Project ID]=$B$5),3),"")
A17: =IFERROR(INDEX(FILTER(tblTasks[Task ID],tblTasks[Project ID]=$B$5),4),"") | B17: =IFERROR(INDEX(FILTER(tblTasks[Task Name],tblTasks[Project ID]=$B$5),4),"") | C17: =IFERROR(INDEX(FILTER(tblTasks[Assigned User],tblTasks[Project ID]=$B$5),4),"") | D17: =IFERROR(INDEX(FILTER(tblTasks[Manual Status],tblTasks[Project ID]=$B$5),4),"") | E17: =IFERROR(INDEX(FILTER(tblTasks[Priority],tblTasks[Project ID]=$B$5),4),"") | F17: =IFERROR(INDEX(FILTER(tblTasks[Progress %],tblTasks[Project ID]=$B$5),4),"") | G17: =IFERROR(INDEX(FILTER(tblTasks[Auto Health],tblTasks[Project ID]=$B$5),4),"") | H17: =IFERROR(INDEX(FILTER(tblTasks[Due Date],tblTasks[Project ID]=$B$5),4),"")
A18: =IFERROR(INDEX(FILTER(tblTasks[Task ID],tblTasks[Project ID]=$B$5),5),"") | B18: =IFERROR(INDEX(FILTER(tblTasks[Task Name],tblTasks[Project ID]=$B$5),5),"") | C18: =IFERROR(INDEX(FILTER(tblTasks[Assigned User],tblTasks[Project ID]=$B$5),5),"") | D18: =IFERROR(INDEX(FILTER(tblTasks[Manual Status],tblTasks[Project ID]=$B$5),5),"") | E18: =IFERROR(INDEX(FILTER(tblTasks[Priority],tblTasks[Project ID]=$B$5),5),"") | F18: =IFERROR(INDEX(FILTER(tblTasks[Progress %],tblTasks[Project ID]=$B$5),5),"") | G18: =IFERROR(INDEX(FILTER(tblTasks[Auto Health],tblTasks[Project ID]=$B$5),5),"") | H18: =IFERROR(INDEX(FILTER(tblTasks[Due Date],tblTasks[Project ID]=$B$5),5),"")
A19: =IFERROR(INDEX(FILTER(tblTasks[Task ID],tblTasks[Project ID]=$B$5),6),"") | B19: =IFERROR(INDEX(FILTER(tblTasks[Task Name],tblTasks[Project ID]=$B$5),6),"") | C19: =IFERROR(INDEX(FILTER(tblTasks[Assigned User],tblTasks[Project ID]=$B$5),6),"") | D19: =IFERROR(INDEX(FILTER(tblTasks[Manual Status],tblTasks[Project ID]=$B$5),6),"") | E19: =IFERROR(INDEX(FILTER(tblTasks[Priority],tblTasks[Project ID]=$B$5),6),"") | F19: =IFERROR(INDEX(FILTER(tblTasks[Progress %],tblTasks[Project ID]=$B$5),6),"") | G19: =IFERROR(INDEX(FILTER(tblTasks[Auto Health],tblTasks[Project ID]=$B$5),6),"") | H19: =IFERROR(INDEX(FILTER(tblTasks[Due Date],tblTasks[Project ID]=$B$5),6),"")
A20: =IFERROR(INDEX(FILTER(tblTasks[Task ID],tblTasks[Project ID]=$B$5),7),"") | B20: =IFERROR(INDEX(FILTER(tblTasks[Task Name],tblTasks[Project ID]=$B$5),7),"") | C20: =IFERROR(INDEX(FILTER(tblTasks[Assigned User],tblTasks[Project ID]=$B$5),7),"") | D20: =IFERROR(INDEX(FILTER(tblTasks[Manual Status],tblTasks[Project ID]=$B$5),7),"") | E20: =IFERROR(INDEX(FILTER(tblTasks[Priority],tblTasks[Project ID]=$B$5),7),"") | F20: =IFERROR(INDEX(FILTER(tblTasks[Progress %],tblTasks[Project ID]=$B$5),7),"") | G20: =IFERROR(INDEX(FILTER(tblTasks[Auto Health],tblTasks[Project ID]=$B$5),7),"") | H20: =IFERROR(INDEX(FILTER(tblTasks[Due Date],tblTasks[Project ID]=$B$5),7),"")
A21: =IFERROR(INDEX(FILTER(tblTasks[Task ID],tblTasks[Project ID]=$B$5),8),"") | B21: =IFERROR(INDEX(FILTER(tblTasks[Task Name],tblTasks[Project ID]=$B$5),8),"") | C21: =IFERROR(INDEX(FILTER(tblTasks[Assigned User],tblTasks[Project ID]=$B$5),8),"") | D21: =IFERROR(INDEX(FILTER(tblTasks[Manual Status],tblTasks[Project ID]=$B$5),8),"") | E21: =IFERROR(INDEX(FILTER(tblTasks[Priority],tblTasks[Project ID]=$B$5),8),"") | F21: =IFERROR(INDEX(FILTER(tblTasks[Progress %],tblTasks[Project ID]=$B$5),8),"") | G21: =IFERROR(INDEX(FILTER(tblTasks[Auto Health],tblTasks[Project ID]=$B$5),8),"") | H21: =IFERROR(INDEX(FILTER(tblTasks[Due Date],tblTasks[Project ID]=$B$5),8),"")
A22: =IFERROR(INDEX(FILTER(tblTasks[Task ID],tblTasks[Project ID]=$B$5),9),"") | B22: =IFERROR(INDEX(FILTER(tblTasks[Task Name],tblTasks[Project ID]=$B$5),9),"") | C22: =IFERROR(INDEX(FILTER(tblTasks[Assigned User],tblTasks[Project ID]=$B$5),9),"") | D22: =IFERROR(INDEX(FILTER(tblTasks[Manual Status],tblTasks[Project ID]=$B$5),9),"") | E22: =IFERROR(INDEX(FILTER(tblTasks[Priority],tblTasks[Project ID]=$B$5),9),"") | F22: =IFERROR(INDEX(FILTER(tblTasks[Progress %],tblTasks[Project ID]=$B$5),9),"") | G22: =IFERROR(INDEX(FILTER(tblTasks[Auto Health],tblTasks[Project ID]=$B$5),9),"") | H22: =IFERROR(INDEX(FILTER(tblTasks[Due Date],tblTasks[Project ID]=$B$5),9),"")
A23: =IFERROR(INDEX(FILTER(tblTasks[Task ID],tblTasks[Project ID]=$B$5),10),"") | B23: =IFERROR(INDEX(FILTER(tblTasks[Task Name],tblTasks[Project ID]=$B$5),10),"") | C23: =IFERROR(INDEX(FILTER(tblTasks[Assigned User],tblTasks[Project ID]=$B$5),10),"") | D23: =IFERROR(INDEX(FILTER(tblTasks[Manual Status],tblTasks[Project ID]=$B$5),10),"") | E23: =IFERROR(INDEX(FILTER(tblTasks[Priority],tblTasks[Project ID]=$B$5),10),"") | F23: =IFERROR(INDEX(FILTER(tblTasks[Progress %],tblTasks[Project ID]=$B$5),10),"") | G23: =IFERROR(INDEX(FILTER(tblTasks[Auto Health],tblTasks[Project ID]=$B$5),10),"") | H23: =IFERROR(INDEX(FILTER(tblTasks[Due Date],tblTasks[Project ID]=$B$5),10),"")
A24: =IFERROR(INDEX(FILTER(tblTasks[Task ID],tblTasks[Project ID]=$B$5),11),"") | B24: =IFERROR(INDEX(FILTER(tblTasks[Task Name],tblTasks[Project ID]=$B$5),11),"") | C24: =IFERROR(INDEX(FILTER(tblTasks[Assigned User],tblTasks[Project ID]=$B$5),11),"") | D24: =IFERROR(INDEX(FILTER(tblTasks[Manual Status],tblTasks[Project ID]=$B$5),11),"") | E24: =IFERROR(INDEX(FILTER(tblTasks[Priority],tblTasks[Project ID]=$B$5),11),"") | F24: =IFERROR(INDEX(FILTER(tblTasks[Progress %],tblTasks[Project ID]=$B$5),11),"") | G24: =IFERROR(INDEX(FILTER(tblTasks[Auto Health],tblTasks[Project ID]=$B$5),11),"") | H24: =IFERROR(INDEX(FILTER(tblTasks[Due Date],tblTasks[Project ID]=$B$5),11),"")
A25: =IFERROR(INDEX(FILTER(tblTasks[Task ID],tblTasks[Project ID]=$B$5),12),"") | B25: =IFERROR(INDEX(FILTER(tblTasks[Task Name],tblTasks[Project ID]=$B$5),12),"") | C25: =IFERROR(INDEX(FILTER(tblTasks[Assigned User],tblTasks[Project ID]=$B$5),12),"") | D25: =IFERROR(INDEX(FILTER(tblTasks[Manual Status],tblTasks[Project ID]=$B$5),12),"") | E25: =IFERROR(INDEX(FILTER(tblTasks[Priority],tblTasks[Project ID]=$B$5),12),"") | F25: =IFERROR(INDEX(FILTER(tblTasks[Progress %],tblTasks[Project ID]=$B$5),12),"") | G25: =IFERROR(INDEX(FILTER(tblTasks[Auto Health],tblTasks[Project ID]=$B$5),12),"") | H25: =IFERROR(INDEX(FILTER(tblTasks[Due Date],tblTasks[Project ID]=$B$5),12),"")
A26: =IFERROR(INDEX(FILTER(tblTasks[Task ID],tblTasks[Project ID]=$B$5),13),"") | B26: =IFERROR(INDEX(FILTER(tblTasks[Task Name],tblTasks[Project ID]=$B$5),13),"") | C26: =IFERROR(INDEX(FILTER(tblTasks[Assigned User],tblTasks[Project ID]=$B$5),13),"") | D26: =IFERROR(INDEX(FILTER(tblTasks[Manual Status],tblTasks[Project ID]=$B$5),13),"") | E26: =IFERROR(INDEX(FILTER(tblTasks[Priority],tblTasks[Project ID]=$B$5),13),"") | F26: =IFERROR(INDEX(FILTER(tblTasks[Progress %],tblTasks[Project ID]=$B$5),13),"") | G26: =IFERROR(INDEX(FILTER(tblTasks[Auto Health],tblTasks[Project ID]=$B$5),13),"") | H26: =IFERROR(INDEX(FILTER(tblTasks[Due Date],tblTasks[Project ID]=$B$5),13),"")
A27: =IFERROR(INDEX(FILTER(tblTasks[Task ID],tblTasks[Project ID]=$B$5),14),"") | B27: =IFERROR(INDEX(FILTER(tblTasks[Task Name],tblTasks[Project ID]=$B$5),14),"") | C27: =IFERROR(INDEX(FILTER(tblTasks[Assigned User],tblTasks[Project ID]=$B$5),14),"") | D27: =IFERROR(INDEX(FILTER(tblTasks[Manual Status],tblTasks[Project ID]=$B$5),14),"") | E27: =IFERROR(INDEX(FILTER(tblTasks[Priority],tblTasks[Project ID]=$B$5),14),"") | F27: =IFERROR(INDEX(FILTER(tblTasks[Progress %],tblTasks[Project ID]=$B$5),14),"") | G27: =IFERROR(INDEX(FILTER(tblTasks[Auto Health],tblTasks[Project ID]=$B$5),14),"") | H27: =IFERROR(INDEX(FILTER(tblTasks[Due Date],tblTasks[Project ID]=$B$5),14),"")
A28: =IFERROR(INDEX(FILTER(tblTasks[Task ID],tblTasks[Project ID]=$B$5),15),"") | B28: =IFERROR(INDEX(FILTER(tblTasks[Task Name],tblTasks[Project ID]=$B$5),15),"") | C28: =IFERROR(INDEX(FILTER(tblTasks[Assigned User],tblTasks[Project ID]=$B$5),15),"") | D28: =IFERROR(INDEX(FILTER(tblTasks[Manual Status],tblTasks[Project ID]=$B$5),15),"") | E28: =IFERROR(INDEX(FILTER(tblTasks[Priority],tblTasks[Project ID]=$B$5),15),"") | F28: =IFERROR(INDEX(FILTER(tblTasks[Progress %],tblTasks[Project ID]=$B$5),15),"") | G28: =IFERROR(INDEX(FILTER(tblTasks[Auto Health],tblTasks[Project ID]=$B$5),15),"") | H28: =IFERROR(INDEX(FILTER(tblTasks[Due Date],tblTasks[Project ID]=$B$5),15),"")
A31: Recent Activity
A32: Date | B32: Type | C32: User | D32: Task | E32: Comment
A33: =IFERROR(INDEX(FILTER(tblActivity[Activity Date],tblActivity[Project ID]=$B$5),1),"") | B33: =IFERROR(INDEX(FILTER(tblActivity[Activity Type],tblActivity[Project ID]=$B$5),1),"") | C33: =IFERROR(INDEX(FILTER(tblActivity[User ID],tblActivity[Project ID]=$B$5),1),"") | D33: =IFERROR(INDEX(FILTER(tblActivity[Task ID],tblActivity[Project ID]=$B$5),1),"") | E33: =IFERROR(INDEX(FILTER(tblActivity[Comment / Update],tblActivity[Project ID]=$B$5),1),"")
A34: =IFERROR(INDEX(FILTER(tblActivity[Activity Date],tblActivity[Project ID]=$B$5),2),"") | B34: =IFERROR(INDEX(FILTER(tblActivity[Activity Type],tblActivity[Project ID]=$B$5),2),"") | C34: =IFERROR(INDEX(FILTER(tblActivity[User ID],tblActivity[Project ID]=$B$5),2),"") | D34: =IFERROR(INDEX(FILTER(tblActivity[Task ID],tblActivity[Project ID]=$B$5),2),"") | E34: =IFERROR(INDEX(FILTER(tblActivity[Comment / Update],tblActivity[Project ID]=$B$5),2),"")
A35: =IFERROR(INDEX(FILTER(tblActivity[Activity Date],tblActivity[Project ID]=$B$5),3),"") | B35: =IFERROR(INDEX(FILTER(tblActivity[Activity Type],tblActivity[Project ID]=$B$5),3),"") | C35: =IFERROR(INDEX(FILTER(tblActivity[User ID],tblActivity[Project ID]=$B$5),3),"") | D35: =IFERROR(INDEX(FILTER(tblActivity[Task ID],tblActivity[Project ID]=$B$5),3),"") | E35: =IFERROR(INDEX(FILTER(tblActivity[Comment / Update],tblActivity[Project ID]=$B$5),3),"")
A36: =IFERROR(INDEX(FILTER(tblActivity[Activity Date],tblActivity[Project ID]=$B$5),4),"") | B36: =IFERROR(INDEX(FILTER(tblActivity[Activity Type],tblActivity[Project ID]=$B$5),4),"") | C36: =IFERROR(INDEX(FILTER(tblActivity[User ID],tblActivity[Project ID]=$B$5),4),"") | D36: =IFERROR(INDEX(FILTER(tblActivity[Task ID],tblActivity[Project ID]=$B$5),4),"") | E36: =IFERROR(INDEX(FILTER(tblActivity[Comment / Update],tblActivity[Project ID]=$B$5),4),"")
A37: =IFERROR(INDEX(FILTER(tblActivity[Activity Date],tblActivity[Project ID]=$B$5),5),"") | B37: =IFERROR(INDEX(FILTER(tblActivity[Activity Type],tblActivity[Project ID]=$B$5),5),"") | C37: =IFERROR(INDEX(FILTER(tblActivity[User ID],tblActivity[Project ID]=$B$5),5),"") | D37: =IFERROR(INDEX(FILTER(tblActivity[Task ID],tblActivity[Project ID]=$B$5),5),"") | E37: =IFERROR(INDEX(FILTER(tblActivity[Comment / Update],tblActivity[Project ID]=$B$5),5),"")
A38: =IFERROR(INDEX(FILTER(tblActivity[Activity Date],tblActivity[Project ID]=$B$5),6),"") | B38: =IFERROR(INDEX(FILTER(tblActivity[Activity Type],tblActivity[Project ID]=$B$5),6),"") | C38: =IFERROR(INDEX(FILTER(tblActivity[User ID],tblActivity[Project ID]=$B$5),6),"") | D38: =IFERROR(INDEX(FILTER(tblActivity[Task ID],tblActivity[Project ID]=$B$5),6),"") | E38: =IFERROR(INDEX(FILTER(tblActivity[Comment / Update],tblActivity[Project ID]=$B$5),6),"")
A39: =IFERROR(INDEX(FILTER(tblActivity[Activity Date],tblActivity[Project ID]=$B$5),7),"") | B39: =IFERROR(INDEX(FILTER(tblActivity[Activity Type],tblActivity[Project ID]=$B$5),7),"") | C39: =IFERROR(INDEX(FILTER(tblActivity[User ID],tblActivity[Project ID]=$B$5),7),"") | D39: =IFERROR(INDEX(FILTER(tblActivity[Task ID],tblActivity[Project ID]=$B$5),7),"") | E39: =IFERROR(INDEX(FILTER(tblActivity[Comment / Update],tblActivity[Project ID]=$B$5),7),"")
A40: =IFERROR(INDEX(FILTER(tblActivity[Activity Date],tblActivity[Project ID]=$B$5),8),"") | B40: =IFERROR(INDEX(FILTER(tblActivity[Activity Type],tblActivity[Project ID]=$B$5),8),"") | C40: =IFERROR(INDEX(FILTER(tblActivity[User ID],tblActivity[Project ID]=$B$5),8),"") | D40: =IFERROR(INDEX(FILTER(tblActivity[Task ID],tblActivity[Project ID]=$B$5),8),"") | E40: =IFERROR(INDEX(FILTER(tblActivity[Comment / Update],tblActivity[Project ID]=$B$5),8),"")
A41: =IFERROR(INDEX(FILTER(tblActivity[Activity Date],tblActivity[Project ID]=$B$5),9),"") | B41: =IFERROR(INDEX(FILTER(tblActivity[Activity Type],tblActivity[Project ID]=$B$5),9),"") | C41: =IFERROR(INDEX(FILTER(tblActivity[User ID],tblActivity[Project ID]=$B$5),9),"") | D41: =IFERROR(INDEX(FILTER(tblActivity[Task ID],tblActivity[Project ID]=$B$5),9),"") | E41: =IFERROR(INDEX(FILTER(tblActivity[Comment / Update],tblActivity[Project ID]=$B$5),9),"")

Sheet Compact_Dashboard
A1: Compact Dashboard
A2: Responsive-style quick view for smaller screens
A3: Home | B3: Exec | C3: Compact | D3: Project | E3: Tasks | F3: Kanban | G3: Gantt | H3: Reports | I3: Master
A5: =COUNTA(tblProjects[Project ID]) | C5: =COUNTIFS(tblProjects[Manual Status],"In Progress") | E5: =COUNTIFS(tblTasks[Auto Health],"Overdue") | G5: =COUNTIFS(tblIssues[Status],"<>Closed",tblIssues[Status],"<>Resolved")
A7: Projects | C7: Active | E7: Overdue | G7: Issues
A10: =COUNTIFS(tblRisks[Status],"<>Closed") | C10: =SUM(tblTimesheets[Hours]) | E10: =COUNTIFS(tblTasks[Manual Status],"Blocked") | G10: =SUM(tblProjects[Actual Cost])-SUM(tblProjects[Budget])
A12: Risks | C12: Hours | E12: Blocked | G12: Budget Var
A15: Next Actions
A16: Type | B16: Project | C16: Item | D16: Owner | E16: Due | F16: Health
A17: Task | B17: =IFERROR(INDEX(tblTasks[Project ID],1),"") | C17: =IFERROR(INDEX(tblTasks[Task Name],1),"") | D17: =IFERROR(INDEX(tblTasks[Assigned User],1),"") | E17: =IFERROR(INDEX(tblTasks[Due Date],1),"") | F17: =IFERROR(INDEX(tblTasks[Auto Health],1),"")
A18: Task | B18: =IFERROR(INDEX(tblTasks[Project ID],2),"") | C18: =IFERROR(INDEX(tblTasks[Task Name],2),"") | D18: =IFERROR(INDEX(tblTasks[Assigned User],2),"") | E18: =IFERROR(INDEX(tblTasks[Due Date],2),"") | F18: =IFERROR(INDEX(tblTasks[Auto Health],2),"")
A19: Task | B19: =IFERROR(INDEX(tblTasks[Project ID],3),"") | C19: =IFERROR(INDEX(tblTasks[Task Name],3),"") | D19: =IFERROR(INDEX(tblTasks[Assigned User],3),"") | E19: =IFERROR(INDEX(tblTasks[Due Date],3),"") | F19: =IFERROR(INDEX(tblTasks[Auto Health],3),"")
A20: Task | B20: =IFERROR(INDEX(tblTasks[Project ID],4),"") | C20: =IFERROR(INDEX(tblTasks[Task Name],4),"") | D20: =IFERROR(INDEX(tblTasks[Assigned User],4),"") | E20: =IFERROR(INDEX(tblTasks[Due Date],4),"") | F20: =IFERROR(INDEX(tblTasks[Auto Health],4),"")
A21: Task | B21: =IFERROR(INDEX(tblTasks[Project ID],5),"") | C21: =IFERROR(INDEX(tblTasks[Task Name],5),"") | D21: =IFERROR(INDEX(tblTasks[Assigned User],5),"") | E21: =IFERROR(INDEX(tblTasks[Due Date],5),"") | F21: =IFERROR(INDEX(tblTasks[Auto Health],5),"")
A22: Task | B22: =IFERROR(INDEX(tblTasks[Project ID],6),"") | C22: =IFERROR(INDEX(tblTasks[Task Name],6),"") | D22: =IFERROR(INDEX(tblTasks[Assigned User],6),"") | E22: =IFERROR(INDEX(tblTasks[Due Date],6),"") | F22: =IFERROR(INDEX(tblTasks[Auto Health],6),"")
A23: Task | B23: =IFERROR(INDEX(tblTasks[Project ID],7),"") | C23: =IFERROR(INDEX(tblTasks[Task Name],7),"") | D23: =IFERROR(INDEX(tblTasks[Assigned User],7),"") | E23: =IFERROR(INDEX(tblTasks[Due Date],7),"") | F23: =IFERROR(INDEX(tblTasks[Auto Health],7),"")
A24: Task | B24: =IFERROR(INDEX(tblTasks[Project ID],8),"") | C24: =IFERROR(INDEX(tblTasks[Task Name],8),"") | D24: =IFERROR(INDEX(tblTasks[Assigned User],8),"") | E24: =IFERROR(INDEX(tblTasks[Due Date],8),"") | F24: =IFERROR(INDEX(tblTasks[Auto Health],8),"")
A25: Task | B25: =IFERROR(INDEX(tblTasks[Project ID],9),"") | C25: =IFERROR(INDEX(tblTasks[Task Name],9),"") | D25: =IFERROR(INDEX(tblTasks[Assigned User],9),"") | E25: =IFERROR(INDEX(tblTasks[Due Date],9),"") | F25: =IFERROR(INDEX(tblTasks[Auto Health],9),"")
A26: Task | B26: =IFERROR(INDEX(tblTasks[Project ID],10),"") | C26: =IFERROR(INDEX(tblTasks[Task Name],10),"") | D26: =IFERROR(INDEX(tblTasks[Assigned User],10),"") | E26: =IFERROR(INDEX(tblTasks[Due Date],10),"") | F26: =IFERROR(INDEX(tblTasks[Auto Health],10),"")
A27: Task | B27: =IFERROR(INDEX(tblTasks[Project ID],11),"") | C27: =IFERROR(INDEX(tblTasks[Task Name],11),"") | D27: =IFERROR(INDEX(tblTasks[Assigned User],11),"") | E27: =IFERROR(INDEX(tblTasks[Due Date],11),"") | F27: =IFERROR(INDEX(tblTasks[Auto Health],11),"")
A28: Task | B28: =IFERROR(INDEX(tblTasks[Project ID],12),"") | C28: =IFERROR(INDEX(tblTasks[Task Name],12),"") | D28: =IFERROR(INDEX(tblTasks[Assigned User],12),"") | E28: =IFERROR(INDEX(tblTasks[Due Date],12),"") | F28: =IFERROR(INDEX(tblTasks[Auto Health],12),"")

Sheet Project_Charter
A1: Project Charter
A2: PMO governance module
A3: Home | B3: Exec | C3: Compact | D3: Project | E3: Tasks | F3: Kanban | G3: Gantt | H3: Reports | I3: Master
A5: Charter ID | B5: Project ID | C5: Business Objective | D5: Scope Summary | E5: Success Criteria | F5: Sponsor | G5: Approval Status | H5: Approved Date
A6: CHR-001 | B6: PRJ-001 | C6: Modernize ERP operations | D6: Replace legacy integration and automate reporting | E6: Stable go-live with <2% defects | F6: USR-001 | G6: Approved | H6: 46147
A7: CHR-002 | B7: PRJ-006 | C7: Regulatory reporting automation | D7: Automate compliance pack generation | E7: On-time monthly regulatory reports | F7: USR-006 | G7: Draft

Sheet Deliverables
A1: Deliverables
A2: PMO governance module
A3: Home | B3: Exec | C3: Compact | D3: Project | E3: Tasks | F3: Kanban | G3: Gantt | H3: Reports | I3: Master
A5: Deliverable ID | B5: Project ID | C5: Deliverable | D5: Owner | E5: Due Date | F5: Status | G5: Acceptance Criteria | H5: Approval Status
A6: DEL-001 | B6: PRJ-001 | C6: Integration design pack | D6: USR-003 | E6: 46190 | F6: In Progress | G6: Signed architecture document | H6: Submitted
A7: DEL-002 | B7: PRJ-002 | C7: Portal beta build | D7: USR-002 | E7: 46207 | F7: Not Started | G7: Beta available to pilot users | H7: Draft
A8: DEL-003 | B8: PRJ-006 | C8: Compliance report template | D8: USR-006 | E8: 46202 | F8: Not Started | G8: Approved by compliance officer | H8: Draft

Sheet Change_Requests
A1: Change Requests
A2: PMO governance module
A3: Home | B3: Exec | C3: Compact | D3: Project | E3: Tasks | F3: Kanban | G3: Gantt | H3: Reports | I3: Master
A5: Change ID | B5: Project ID | C5: Title | D5: Requester | E5: Request Date | F5: Status | G5: Priority | H5: Estimated Cost | I5: Reason
A6: CR-001 | B6: PRJ-002 | C6: Add biometric login | D6: USR-001 | E6: 46178 | F6: Under Review | G6: High | H6: 65000 | I6: Security requirement
A7: CR-002 | B7: PRJ-004 | C7: Add regional approval route | D7: USR-006 | E7: 46180 | F7: Draft | G7: Medium | H7: 25000 | I7: Ops request

Sheet Approvals
A1: Approvals
A2: PMO governance module
A3: Home | B3: Exec | C3: Compact | D3: Project | E3: Tasks | F3: Kanban | G3: Gantt | H3: Reports | I3: Master
A5: Approval ID | B5: Project ID | C5: Approval Item | D5: Requester | E5: Approver | F5: Submitted Date | G5: Status | H5: Notes
A6: APR-001 | B6: PRJ-001 | C6: Architecture sign-off | D6: USR-001 | E6: USR-007 | F6: 46181 | G6: Submitted | H6: Pending finance review
A7: APR-002 | B7: PRJ-002 | C7: Security design | D7: USR-001 | E7: USR-005 | F7: 46179 | G7: Rework Required | H7: Need auth details
A8: APR-003 | B8: PRJ-005 | C8: Closure approval | D8: USR-001 | E8: USR-007 | F8: 46175 | G8: Approved | H8: Closed

Sheet RACI_Matrix
A1: RACI Matrix
A2: PMO governance module
A3: Home | B3: Exec | C3: Compact | D3: Project | E3: Tasks | F3: Kanban | G3: Gantt | H3: Reports | I3: Master
A5: RACI ID | B5: Project ID | C5: Workstream | D5: Activity | E5: Responsible | F5: Accountable | G5: Consulted | H5: Informed
A6: RACI-001 | B6: PRJ-001 | C6: Integration | D6: Oracle connector | E6: USR-002 | F6: USR-001 | G6: USR-005 | H6: USR-007
A7: RACI-002 | B7: PRJ-002 | C7: Security | D7: Authentication | E7: USR-002 | F7: USR-001 | G7: USR-005 | H7: USR-006
A8: RACI-003 | B8: PRJ-006 | C8: Compliance | D8: Report matrix | E8: USR-006 | F8: USR-001 | G8: USR-007 | H8: USR-004

Sheet Stakeholders
A1: Stakeholders
A2: PMO governance module
A3: Home | B3: Exec | C3: Compact | D3: Project | E3: Tasks | F3: Kanban | G3: Gantt | H3: Reports | I3: Master
A5: Stakeholder ID | B5: Project ID | C5: Name | D5: Role | E5: Influence | F5: Cadence | G5: Owner
A6: STK-001 | B6: PRJ-001 | C6: Finance Sponsor | D6: Sponsor | E6: High | F6: Weekly | G6: USR-001
A7: STK-002 | B7: PRJ-002 | C7: Sales Head | D7: Sponsor | E7: High | F7: Weekly | G7: USR-001
A8: STK-003 | B8: PRJ-006 | C8: Compliance Officer | D8: Approver | E8: Critical | F8: Twice Weekly | G8: USR-006

Sheet Communication_Plan
A1: Communication Plan
A2: PMO governance module
A3: Home | B3: Exec | C3: Compact | D3: Project | E3: Tasks | F3: Kanban | G3: Gantt | H3: Reports | I3: Master
A5: Comm ID | B5: Project ID | C5: Communication | D5: Channel | E5: Frequency | F5: Owner | G5: Audience
A6: COM-001 | B6: PRJ-001 | C6: Steering update | D6: Meeting | E6: Weekly | F6: USR-001 | G6: Sponsor group
A7: COM-002 | B7: PRJ-002 | C7: Build status | D7: Email | E7: Twice Weekly | F7: USR-002 | G7: Project team
A8: COM-003 | B8: PRJ-006 | C8: Regulatory review | D8: Meeting | E8: Weekly | F8: USR-006 | G8: Compliance team

Sheet Meeting_Actions
A1: Meeting Actions
A2: PMO governance module
A3: Home | B3: Exec | C3: Compact | D3: Project | E3: Tasks | F3: Kanban | G3: Gantt | H3: Reports | I3: Master
A5: Action ID | B5: Project ID | C5: Action Item | D5: Owner | E5: Due Date | F5: Status | G5: Notes
A6: ACT-001 | B6: PRJ-001 | C6: Confirm Oracle grants | D6: USR-002 | E6: 46184 | F6: Open | G6: DBA dependency
A7: ACT-002 | B7: PRJ-002 | C7: Resolve security comments | D7: USR-001 | E7: 46183 | F7: Open | G7: Auth review
A8: ACT-003 | B8: PRJ-003 | C8: Assign data owners | D8: USR-004 | E8: 46187 | F8: Open | G8: Governance

Sheet Decision_Log
A1: Decision Log
A2: PMO governance module
A3: Home | B3: Exec | C3: Compact | D3: Project | E3: Tasks | F3: Kanban | G3: Gantt | H3: Reports | I3: Master
A5: Decision ID | B5: Project ID | C5: Decision | D5: Owner | E5: Decision Date | F5: Status | G5: Category
A6: DEC-001 | B6: PRJ-001 | C6: Use CDB/PDB Oracle architecture | D6: USR-001 | E6: 46172 | F6: Approved | G6: Architecture
A7: DEC-002 | B7: PRJ-002 | C7: Use SSO provider | D7: USR-001 | E7: 46180 | F7: Pending | G7: Security
A8: DEC-003 | B8: PRJ-006 | C8: Monthly compliance pack format | D8: USR-006 | E8: 46182 | F8: Draft | G8: Reporting

Sheet Lessons_Learned
A1: Lessons Learned
A2: PMO governance module
A3: Home | B3: Exec | C3: Compact | D3: Project | E3: Tasks | F3: Kanban | G3: Gantt | H3: Reports | I3: Master
A5: Lesson ID | B5: Project ID | C5: Lesson | D5: Owner | E5: Date | F5: Category
A6: LL-001 | B6: PRJ-005 | C6: Design approval earlier reduces rework | D6: USR-003 | E6: 46177 | F6: Process
A7: LL-002 | B7: PRJ-001 | C7: DBA access must be requested before sprint start | D7: USR-002 | E7: 46181 | F7: Dependency

Sheet Data_Dictionary
A1: Data Dictionary
A2: Purpose of each worksheet
A3: Home | B3: Exec | C3: Compact | D3: Project | E3: Tasks | F3: Kanban | G3: Gantt | H3: Reports | I3: Master
A5: Sheet | B5: Purpose
A6: Home | B6: Project management environment module
A7: Portfolio_Dashboard | B7: Project management environment module
A8: Project_Workspace | B8: Project management environment module
A9: Projects | B9: Project management environment module
A10: Tasks | B10: Project management environment module
A11: Subtasks | B11: Project management environment module
A12: Milestones | B12: Project management environment module
A13: Issues | B13: Project management environment module
A14: Risks | B14: Project management environment module
A15: Timesheets | B15: Project management environment module
A16: Calendar | B16: Project management environment module
... A40: Data_Dictionary | B40: Project management environment module
